Workbook
Name Assumptions_CurrentAge: Assumptions!$B$7
Name Assumptions_RetirementAge: Assumptions!$B$8
Name Assumptions_LifeExpectancy: Assumptions!$B$9
Name Assumptions_Province: Assumptions!$B$10
Name Assumptions_EmploymentIncome: Assumptions!$B$13
Name Assumptions_StillWorking: Assumptions!$B$14
Name Assumptions_CppMonthly: Assumptions!$B$17
Name Assumptions_CppStartAge: Assumptions!$B$18
Name Assumptions_OasMonthly: Assumptions!$B$19
Name Assumptions_OasStartAge: Assumptions!$B$20
Name Assumptions_PensionType: Assumptions!$B$23
Name Assumptions_DbPensionAnnual: Assumptions!$B$24
Name Assumptions_DbPensionStartAge: Assumptions!$B$25
Name Assumptions_DbPensionIndexed: Assumptions!$B$26
Name Assumptions_RrspBalance: Assumptions!$B$29
Name Assumptions_TfsaBalance: Assumptions!$B$30
Name Assumptions_NonRegBalance: Assumptions!$B$31
Name Assumptions_NonRegCostBasis: Assumptions!$B$32
Name Assumptions_OtherAssets: Assumptions!$B$33
Name Assumptions_RealEstateValue: Assumptions!$B$36
Name Assumptions_IsPrimaryRes: Assumptions!$B$37
Name Assumptions_RealEstateCost: Assumptions!$B$38
Name Assumptions_MortgageBalance: Assumptions!$B$41
Name Assumptions_MortgageRate: Assumptions!$B$42
Name Assumptions_MortgageYears: Assumptions!$B$43
Name Assumptions_ConsumerDebt: Assumptions!$B$44
Name Assumptions_ConsumerDebtRate: Assumptions!$B$45
Name Assumptions_ConsumerPayoffAge: Assumptions!$B$46
Name Assumptions_OtherDebt: Assumptions!$B$47
Name Assumptions_OtherDebtRate: Assumptions!$B$48
Name Assumptions_OtherPayoffAge: Assumptions!$B$49
Name Assumptions_MonthlyExpenses: Assumptions!$B$52
Name Assumptions_ExpenseReduction: Assumptions!$B$53
Name Assumptions_Inflation: Assumptions!$B$54
Name Assumptions_RealReturn: Assumptions!$B$55
Name Assumptions_TfsaReturn: Assumptions!$B$56
Name Assumptions_NonRegReturn: Assumptions!$B$57
Name Assumptions_MeltdownEnabled: Assumptions!$B$61
Name Assumptions_MeltdownStartAge: Assumptions!$B$62
Name Assumptions_MeltdownTargetAge: Assumptions!$B$63
Name Assumptions_MeltdownAnnual: Assumptions!$B$64
Name Assumptions_CapGainsRate: Assumptions!$B$67
Name Assumptions_TfsaAnnualLimit: Assumptions!$B$68
Name Assumptions_OasClawbackThresh: Assumptions!$B$69
Name Assumptions_OasClawbackRate: Assumptions!$B$70
Name Assumptions_OasMaxAnnual: Assumptions!$B$71
Name FedBracketMin: 'Tax Engine'!$A$5:$A$9
Name FedBracketMax: 'Tax Engine'!$B$5:$B$9
Name FedBracketRate: 'Tax Engine'!$C$5:$C$9
Name ProvBracketMin: 'Tax Engine'!$A$12:$A$16
Name ProvBracketMax: 'Tax Engine'!$B$12:$B$16
Name ProvBracketRate: 'Tax Engine'!$C$12:$C$16
Name FedBasicPersonal: 'Tax Engine'!$B$19
Name ProvBasicPersonal: 'Tax Engine'!$C$19
Name FedAgeAmount: 'Tax Engine'!$B$20
Name ProvAgeAmount: 'Tax Engine'!$C$20
Name FedAgeThreshold: 'Tax Engine'!$B$21
Name ProvAgeThreshold: 'Tax Engine'!$C$21
Name FedAgeClawRate: 'Tax Engine'!$B$22
Name ProvAgeClawRate: 'Tax Engine'!$C$22

Sheet Assumptions
A1: These are YOUR numbers — everything about your life, income, savings, and debts. Change any blue number and the entire workbook recalculates. Yellow cells are the most important assumptions to experiment with.
A4: ASSUMPTIONS | B4: My Plan | C4: What it means
A6: Personal
A7: Current Age | B7: 34 | C7: Your age today — the starting point for all projections
A8: Retirement Age | B8: 65 | C8: When you plan to stop working and draw from savings
A9: Life Expectancy | B9: 90 | C9: How far we project — plan conservatively (longer = safer)
A10: Province | B10: ON | C10: Used for provincial tax brackets, credits, and surtax
A12: Income
A13: Employment Income | B13: 100000 | C13: Current annual gross salary or self-employment income
A14: Still Working | B14: 1 | C14: 1 = currently employed, 0 = already retired
A16: Government Benefits
A17: CPP Monthly at 65 | B17: 1365 | C17: Estimated CPP pension per month if you start at age 65
A18: CPP Start Age | B18: 65 | C18: When you start CPP (60–70). Early = smaller; late = larger
A19: OAS Monthly at 65 | B19: 713 | C19: Estimated OAS pension per month at age 65
A20: OAS Start Age | B20: 65 | C20: When you start OAS (65–70). Deferring increases by 0.6%/mo
A22: Pension
A23: Pension Type | B23: none | C23: "db" = defined benefit, "dc" = defined contribution, "none"
A24: DB Pension Annual | B24: 0 | C24: Annual DB pension amount at start age (before inflation)
A25: DB Pension Start Age | B25: 65 | C25: Age when DB pension payments begin
A26: DB Pension Indexed | B26: 0 | C26: 1 = pension grows with inflation, 0 = fixed dollar amount
A28: Account Balances
A29: RRSP Balance | B29: 200000 | C29: Combined RRSP + RRIF + DC Pension + LIRA balances
A30: TFSA Balance | B30: 80000 | C30: Tax-Free Savings Account balance
A31: Non-Reg Balance | B31: 10000 | C31: Non-registered investments + cash savings
A32: Non-Reg Cost Basis | B32: 10000 | C32: What you originally paid — used to calculate capital gains tax
A33: Other Assets | B33: 0 | C33: Other registered accounts + miscellaneous assets
A35: Real Estate
A36: Real Estate Value | B36: 800000 | C36: Current market value of your home
A37: Is Primary Residence | B37: 1 | C37: 1 = primary residence (exempt from cap gains), 0 = investment
A38: Est. Cost Basis | B38: 0 | C38: Purchase price (for cap gains if not primary residence)
A40: Liabilities
A41: Mortgage Balance | B41: 400000 | C41: Remaining mortgage principal
A42: Mortgage Rate | B42: 0.04 | C42: Annual mortgage interest rate
A43: Mortgage Years Left | B43: 20 | C43: Years remaining on mortgage
A44: Consumer Debt | B44: 0 | C44: Credit cards, lines of credit, car loans, etc.
A45: Consumer Debt Rate | B45: 0.08 | C45: Average annual interest rate on consumer debt
A46: Consumer Payoff Age | B46: 70 | C46: Target age to be consumer debt-free
A47: Other Debt | B47: 0 | C47: Student loans, family loans, other liabilities
A48: Other Debt Rate | B48: 0 | C48: Average annual interest rate on other debt
A49: Other Payoff Age | B49: 70 | C49: Target age to be completely debt-free
A51: Expenses & Returns
A52: Monthly Expenses | B52: 3000 | C52: Total monthly living expenses (housing, food, transport, etc.)
A53: Expense Reduction | B53: 0.1 | C53: How much expenses drop in retirement (no commute, paid-off home)
A54: Inflation Rate | B54: 0.025 | C54: Expected annual price increases (BoC target = 2%)
A55: Real Return (RRSP) | B55: 0.04 | C55: Investment return above inflation for RRSP accounts
A56: TFSA Return | B56: 0.04 | C56: Investment return above inflation for TFSA
A57: Non-Reg Return | B57: 0.04 | C57: Investment return above inflation for non-registered accounts
A59: Withdrawal Strategy
A60: Withdrawal Order | B60: TFSA > NonReg > RRSP > Other | C60: TFSA first (tax-free), then NonReg, then RRSP (most taxed)
A61: RRSP Meltdown Enabled | B61: 0 | C61: 1 = gradually draw down RRSP before 72, 0 = wait for RRIF
A62: Meltdown Start Age | B62: 65 | C62: Age to start RRSP meltdown withdrawals
A63: Meltdown Target Age | B63: 71 | C63: Age to finish meltdown (must be ≤71, before RRIF kicks in)
A64: Meltdown Annual | B64: 0 | C64: Annual meltdown withdrawal amount
A66: Tax Constants
A67: Capital Gains Inclusion | B67: 0.5 | C67: Fraction of capital gains that are taxable (currently 50%)
A68: TFSA Annual Limit | B68: 7000 | C68: Maximum annual TFSA contribution room
A69: OAS Clawback Threshold | B69: 93454 | C69: Income above this triggers OAS clawback at 15%
A70: OAS Clawback Rate | B70: 0.15 | C70: Rate at which OAS is clawed back (15%)
A71: OAS Max Annual | B71: 8881 | C71: Maximum annual OAS benefit (for clawback cap)
A73: Change any blue value → entire workbook recalculates.
A74: Yellow cells = key assumptions to sensitivity-test.

Sheet CPP-OAS Verify
A1: This sheet shows exactly how your CPP and OAS payments are calculated — the adjustment for starting early or late, inflation indexing, and the OAS clawback check.
A4: CPP Benefit Calculation
A5: Monthly at 65 | B5: =Assumptions_CppMonthly
A6: Start Age | B6: =Assumptions_CppStartAge
A7: Months from 65 | B7: =(Assumptions_CppStartAge-65)*12
A8: Early Reduction/mo | B8: =CppEarlyReduction
A9: Late Increase/mo | B9: =CppLateIncrease
A10: Adjustment Factor | B10: =IF((Assumptions_CppStartAge-65)*12<0, 1+(Assumptions_CppStartAge-65)*12*CppEarlyReduction, 1+(Assumptions_CppStartAge-65)*12*CppLateIncrease)
A11: Annual at Start Age | B11: =Assumptions_CppMonthly*12*IF((Assumptions_CppStartAge-65)*12<0, 1+(Assumptions_CppStartAge-65)*12*CppEarlyReduction, 1+(Assumptions_CppStartAge-65)*12*CppLateIncrease)
A13: OAS Benefit Calculation
A14: Monthly at 65 | B14: =Assumptions_OasMonthly
A15: Start Age | B15: =Assumptions_OasStartAge
A16: Years Deferred | B16: =MAX(0,MIN(Assumptions_OasStartAge,OasMaxDeferAge)-OasStdStartAge)
A17: Deferral Bonus/mo | B17: =OasDeferralBonus
A18: Deferral Multiplier | B18: =1+MAX(0,MIN(Assumptions_OasStartAge,OasMaxDeferAge)-OasStdStartAge)*12*OasDeferralBonus
A19: Annual at Start Age | B19: =Assumptions_OasMonthly*12*(1+MAX(0,MIN(Assumptions_OasStartAge,OasMaxDeferAge)-OasStdStartAge)*12*OasDeferralBonus)
A20: OAS Clawback Thresh. | B20: =Assumptions_OasClawbackThresh
A22: Age | B22: CPP (Formula) | C22: CPP (JS Engine) | D22: OAS (Formula) | E22: OAS (JS Engine)
A23: 34 | B23: ='Projection'!F6 | C23: 0 | D23: ='Projection'!G6 | E23: 0
A24: 39 | B24: ='Projection'!F11 | C24: 0 | D24: ='Projection'!G11 | E24: 0
A25: 44 | B25: ='Projection'!F16 | C25: 0 | D25: ='Projection'!G16 | E25: 0
A26: 49 | B26: ='Projection'!F21 | C26: 0 | D26: ='Projection'!G21 | E26: 0
A27: 54 | B27: ='Projection'!F26 | C27: 0 | D27: ='Projection'!G26 | E27: 0
A28: 59 | B28: ='Projection'!F31 | C28: 0 | D28: ='Projection'!G31 | E28: 0
A29: 64 | B29: ='Projection'!F36 | C29: 0 | D29: ='Projection'!G36 | E29: 0
A30: 65 | B30: ='Projection'!F37 | C30: 35217 | D30: ='Projection'!G37 | E30: 18395
A31: 69 | B31: ='Projection'!F41 | C31: 38873 | D31: ='Projection'!G41 | E31: 20305
A32: 74 | B32: ='Projection'!F46 | C32: 43981 | D32: ='Projection'!G46 | E32: 19650
A33: 79 | B33: ='Projection'!F51 | C33: 49761 | D33: ='Projection'!G51 | E33: 21085
A34: 84 | B34: ='Projection'!F56 | C34: 56300 | D34: ='Projection'!G56 | E34: 22758
A35: 89 | B35: ='Projection'!F61 | C35: 63698 | D35: ='Projection'!G61 | E35: 24709
A37: COLUMN DICTIONARY
A38: Monthly at 65 | B38: Your estimated CPP/OAS monthly payment if starting at the standard age of 65
A39: Months from 65 | B39: Number of months you are starting early (negative) or late (positive) versus 65
A40: Adjustment Factor | B40: Multiplier applied to your benefit: <1 if early, >1 if late
A41: Annual at Start Age | B41: Your first-year annual CPP/OAS payment after the early/late adjustment
A42: Clawback Threshold | B42: If total income exceeds this, OAS is reduced at 15% on the excess
A43: CPP (Formula) | B43: CPP value from the live Excel formula (recalculates if you change assumptions)
A44: CPP (JS Engine) | B44: CPP value from the app's JavaScript engine (static snapshot for comparison)

Sheet Tax Engine
A1: This is how Canadian income tax works, bracket by bracket. You pay a low rate on your first dollars of income, and higher rates on additional income. Credits reduce the tax you owe.
A4: Federal Brackets | B4: Max | C4: Rate
A5: 0 | B5: 57375 | C5: 0.145
A6: 57375 | B6: 114750 | C6: 0.205
A7: 114750 | B7: 177882 | C7: 0.26
A8: 177882 | B8: 253414 | C8: 0.29
A9: 253414 | B9: 999999999 | C9: 0.33
A11: Ontario Brackets | B11: Max | C11: Rate
A12: 0 | B12: 52886 | C12: 0.0505
A13: 52886 | B13: 105775 | C13: 0.0915
A14: 105775 | B14: 150000 | C14: 0.1116
A15: 150000 | B15: 220000 | C15: 0.1216
A16: 220000 | B16: 999999999 | C16: 0.1316
A18: Credits | B18: Federal | C18: ON
A19: Basic Personal | B19: 16129 | C19: 12747
A20: Age Amount | B20: 9028 | C20: 6223
A21: Age Income Threshold | B21: 45522 | C21: 46330
A22: Age Clawback Rate | B22: 0.15 | C22: 0.15
A23: Pension Credit | B23: 2000 | C23: 1762
A24: Credit Rate | B24: 0.145 | C24: 0.0505
A26: ON Surtax
A27: Surtax Threshold 1 | B27: 5710
A28: Surtax Rate 1 | B28: 0.2
A29: Surtax Threshold 2 | B29: 7307
A30: Surtax Rate 2 | B30: 0.36
A32: CPP/OAS Parameters
A33: CPP Early Reduction/mo | B33: 0.006
A34: CPP Late Increase/mo | B34: 0.007
A35: OAS Deferral Bonus/mo | B35: 0.006
A36: OAS Max Defer Age | B36: 70
A37: OAS Start Age | B37: 65
A39: COLUMN DICTIONARY
A40: Bracket Min | B40: The income threshold where this tax bracket begins
A41: Bracket Max | B41: The income threshold where this tax bracket ends
A42: Rate | B42: Tax rate applied to income within this bracket
A43: Basic Personal | B43: Income amount everyone can earn tax-free (non-refundable credit)
A44: Age Amount | B44: Extra tax credit available at age 65+ (income-tested)
A45: Age Income Thresh. | B45: Income level where the age amount starts being clawed back
A46: Pension Credit | B46: Tax credit on first $2,000 of eligible pension/RRIF income
A47: Credit Rate | B47: Lowest bracket rate used to convert credits to tax savings
A48: Surtax | B48: Additional tax some provinces charge on top of basic provincial tax
A49: Effective Rate | B49: Your actual overall tax rate (total tax / total income)

Sheet Projection
A1: This is your complete financial life, one row per year from today until life expectancy. Every number is a formula — change an assumption and watch your entire future recalculate. Green surplus = saving money. Red = drawing down. Portfolio hits $0 = trouble.
A4: YEAR-BY-YEAR PROJECTION
A5: Age | B5: Year | C5: Retired? | D5: Inflation Factor | E5: Employment | F5: CPP | G5: OAS Gross | H5: Pension | I5: RRIF Min | J5: Meltdown | K5: Base RRSP Wd | L5: Taxable Before Grossup | M5: Expenses | N5: Mortgage Pmt | O5: Debt Pmt | P5: Total Need | Q5: Tax on Known | R5: After-Tax Known | S5: Shortfall | T5: TFSA Wd | U5: After TFSA | V5: NonReg Wd | W5: After NonReg | X5: Marginal Rate | Y5: RRSP Grossup | Z5: Total RRSP Wd | AA5: Other Wd | AB5: OAS Clawback | AC5: OAS Net | AD5: NonReg Gain | AE5: Total Taxable | AF5: Federal Tax | AG5: Provincial Tax | AH5: Total Tax | AI5: After-Tax Income | AJ5: Surplus | AK5: TFSA Deposit | AL5: RRSP Bal | AM5: TFSA Bal | AN5: NonReg Bal | AO5: Other Bal | AP5: Mortgage Bal | AQ5: Total Portfolio | AR5: Net Worth | AS5: NonReg Cost Basis
A6: =Assumptions_CurrentAge | B6: =2026+(A6-Assumptions_CurrentAge) | C6: =IF(A6>=Assumptions_RetirementAge,1,0) | D6: =(1+Assumptions_Inflation)^(A6-Assumptions_CurrentAge) | E6: =IF(AND(C6=0,Assumptions_StillWorking=1),Assumptions_EmploymentIncome*D6,0) | F6: =IF(A6>=Assumptions_CppStartAge, Assumptions_CppMonthly*12*IF((Assumptions_CppStartAge-65)*12<0, 1+(Assumptions_CppStartAge-65)*12*CppEarlyReduction, 1+(Assumptions_CppStartAge-65)*12*CppLateIncrease)*D6, 0) | G6: =IF(A6>=Assumptions_OasStartAge, Assumptions_OasMonthly*12*(1+MAX(0, MIN(Assumptions_OasStartAge, OasMaxDeferAge)-OasStdStartAge)*12*OasDeferralBonus)*D6, 0) | H6: =IF(AND(Assumptions_PensionType="db",A6>=Assumptions_DbPensionStartAge), IF(Assumptions_DbPensionIndexed=1, Assumptions_DbPensionAnnual*D6, Assumptions_DbPensionAnnual), 0) | I6: =IF(AND(A6>=72,Assumptions_RrspBalance>0), VLOOKUP(MIN(A6,95),RrifRates,2,TRUE)*Assumptions_RrspBalance, 0) | J6: =IF(AND(Assumptions_MeltdownEnabled=1,A6>=Assumptions_MeltdownStartAge,A6<Assumptions_MeltdownTargetAge), MIN(Assumptions_MeltdownAnnual,Assumptions_RrspBalance), 0) | K6: =MIN(MAX(I6,J6),Assumptions_RrspBalance) | L6: =E6+F6+G6+H6+K6 | M6: =IF(C6=1, Assumptions_MonthlyExpenses*12*(1-Assumptions_ExpenseReduction), Assumptions_MonthlyExpenses*12)*D6 | N6: =IF(AND(Assumptions_MortgageBalance>0, (A6-Assumptions_CurrentAge)<Assumptions_MortgageYears), IF(Assumptions_MortgageRate=0, Assumptions_MortgageBalance/MAX(1,Assumptions_MortgageYears-(A6-Assumptions_CurrentAge)), Assumptions_MortgageBalance*Assumptions_MortgageRate*(1+Assumptions_MortgageRate)^MAX(1,Assumptions_MortgageYears-(A6-Assumptions_CurrentAge))/((1+Assumptions_MortgageRate)^MAX(1,Assumptions_MortgageYears-(A6-Assumptions_CurrentAge))-1)), 0) | O6: =IF(AND(Assumptions_ConsumerDebt>0, A6<Assumptions_ConsumerPayoffAge), IF(Assumptions_ConsumerDebtRate=0, Assumptions_ConsumerDebt/MAX(1,Assumptions_ConsumerPayoffAge-Assumptions_CurrentAge-(A6-Assumptions_CurrentAge)), Assumptions_ConsumerDebt*Assumptions_ConsumerDebtRate*(1+Assumptions_ConsumerDebtRate)^MAX(1,Assumptions_ConsumerPayoffAge-Assumptions_CurrentAge-(A6-Assumptions_CurrentAge))/((1+Assumptions_ConsumerDebtRate)^MAX(1,Assumptions_ConsumerPayoffAge-Assumptions_CurrentAge-(A6-Assumptions_CurrentAge))-1)), 0)+IF(AND(Assumptions_OtherDebt>0, A6<Assumptions_OtherPayoffAge), IF(Assumptions_OtherDebtRate=0, Assumptions_OtherDebt/MAX(1,Assumptions_OtherPayoffAge-Assumptions_CurrentAge-(A6-Assumptions_CurrentAge)), Assumptions_OtherDebt*Assumptions_OtherDebtRate*(1+Assumptions_OtherDebtRate)^MAX(1,Assumptions_OtherPayoffAge-Assumptions_CurrentAge-(A6-Assumptions_CurrentAge))/((1+Assumptions_OtherDebtRate)^MAX(1,Assumptions_OtherPayoffAge-Assumptions_CurrentAge-(A6-Assumptions_CurrentAge))-1)), 0) | P6: =M6+N6+O6 | Q6: =IF(L6<=0, 0, MAX(0, SUMPRODUCT(MAX(MIN(L6,FedBracketMax)-FedBracketMin,0)*FedBracketRate) - (FedBasicPersonal + IF(A6>=65, MAX(0, FedAgeAmount - MAX(0, L6-FedAgeThreshold)*FedAgeClawRate), 0) + IF(OR(H6>0, I6>0), FedPensionCredit, 0)) * FedCreditRate)) | R6: =L6-Q6 | S6: =MAX(0,P6-R6) | T6: =MIN(S6,Assumptions_TfsaBalance) | U6: =MAX(0,S6-T6) | V6: =MIN(U6,Assumptions_NonRegBalance) | W6: =MAX(0,U6-V6) | X6: =INDEX(FedBracketRate,MATCH(L6,FedBracketMin,1))+INDEX(ProvBracketRate,MATCH(L6,ProvBracketMin,1)) | Y6: =IF(W6>0, MIN(IF(X6>=1, W6, W6/(1-X6)), MAX(0,Assumptions_RrspBalance-K6)), 0) | Z6: =K6+Y6 | AA6: =IF(W6>Y6*(1-X6), MIN(MAX(0,W6-Y6*(1-X6)),Assumptions_OtherAssets), 0) | AB6: =MIN(Assumptions_OasMaxAnnual, MAX(0,(E6+F6+G6+H6+Z6-Assumptions_OasClawbackThresh)*Assumptions_OasClawbackRate)) | AC6: =MAX(0,G6-AB6) | AD6: =V6*IF(Assumptions_NonRegBalance>0, MAX(0,1-Assumptions_NonRegCostBasis/Assumptions_NonRegBalance), 0)*Assumptions_CapGainsRate | AE6: =E6+F6+AC6+H6+Z6+AD6 | AF6: =MAX(0, SUMPRODUCT(MAX(MIN(AE6,FedBracketMax)-FedBracketMin,0)*FedBracketRate) - (FedBasicPersonal + IF(A6>=65, MAX(0, FedAgeAmount - MAX(0, AE6-FedAgeThreshold)*FedAgeClawRate), 0) + IF(OR(H6>0, I6>0), FedPensionCredit, 0)) * FedCreditRate) | AG6: =MAX(0, SUMPRODUCT(MAX(MIN(AE6,ProvBracketMax)-ProvBracketMin,0)*ProvBracketRate) - (ProvBasicPersonal + IF(A6>=65, MAX(0, ProvAgeAmount - MAX(0, AE6-ProvAgeThreshold)*ProvAgeClawRate), 0) + IF(OR(H6>0, I6>0), ProvPensionCredit, 0)) * ProvCreditRate) + MAX(0, (MAX(0, SUMPRODUCT(MAX(MIN(AE6,ProvBracketMax)-ProvBracketMin,0)*ProvBracketRate) - (ProvBasicPersonal + IF(A6>=65, MAX(0, ProvAgeAmount - MAX(0, AE6-ProvAgeThreshold)*ProvAgeClawRate), 0) + IF(OR(H6>0, I6>0), ProvPensionCredit, 0)) * ProvCreditRate)-SurtaxThreshold1)*SurtaxRate1) + MAX(0, (MAX(0, SUMPRODUCT(MAX(MIN(AE6,ProvBracketMax)-ProvBracketMin,0)*ProvBracketRate) - (ProvBasicPersonal + IF(A6>=65, MAX(0, ProvAgeAmount - MAX(0, AE6-ProvAgeThreshold)*ProvAgeClawRate), 0) + IF(OR(H6>0, I6>0), ProvPensionCredit, 0)) * ProvCreditRate)-SurtaxThreshold2)*SurtaxRate2) | AH6: =AF6+AG6 | AI6: =E6+F6+AC6+H6+Z6+T6+V6+AA6-AH6 | AJ6: =AI6-M6-N6-O6 | AK6: =IF(AJ6>0, MIN(AJ6, Assumptions_TfsaAnnualLimit), 0) | AL6: =MAX(0,Assumptions_RrspBalance-Z6)*(1+Assumptions_RealReturn) | AM6: =MAX(0,Assumptions_TfsaBalance-T6+AK6)*(1+Assumptions_TfsaReturn) | AN6: =MAX(0,Assumptions_NonRegBalance-V6+MAX(0,AJ6-AK6))*(1+Assumptions_NonRegReturn) | AO6: =MAX(0,Assumptions_OtherAssets-AA6)*(1+Assumptions_RealReturn) | AP6: =IF(N6>0, MAX(0, Assumptions_MortgageBalance*(1+Assumptions_MortgageRate)-N6), 0) | AQ6: =AL6+AM6+AN6+AO6 | AR6: =AQ6+Assumptions_RealEstateValue-AP6 | AS6: =MAX(0,Assumptions_NonRegCostBasis*MAX(0,Assumptions_NonRegBalance-V6)/IF(Assumptions_NonRegBalance>0,Assumptions_NonRegBalance,1))+MAX(0,AJ6-AK6)
A7: =A6+1 | B7: =2026+(A7-Assumptions_CurrentAge) | C7: =IF(A7>=Assumptions_RetirementAge,1,0) | D7: =(1+Assumptions_Inflation)^(A7-Assumptions_CurrentAge) | E7: =IF(AND(C7=0,Assumptions_StillWorking=1),Assumptions_EmploymentIncome*D7,0) | F7: =IF(A7>=Assumptions_CppStartAge, Assumptions_CppMonthly*12*IF((Assumptions_CppStartAge-65)*12<0, 1+(Assumptions_CppStartAge-65)*12*CppEarlyReduction, 1+(Assumptions_CppStartAge-65)*12*CppLateIncrease)*D7, 0) | G7: =IF(A7>=Assumptions_OasStartAge, Assumptions_OasMonthly*12*(1+MAX(0, MIN(Assumptions_OasStartAge, OasMaxDeferAge)-OasStdStartAge)*12*OasDeferralBonus)*D7, 0) | H7: =IF(AND(Assumptions_PensionType="db",A7>=Assumptions_DbPensionStartAge), IF(Assumptions_DbPensionIndexed=1, Assumptions_DbPensionAnnual*D7, Assumptions_DbPensionAnnual), 0) | I7: =IF(AND(A7>=72,AL6>0), VLOOKUP(MIN(A7,95),RrifRates,2,TRUE)*AL6, 0) | J7: =IF(AND(Assumptions_MeltdownEnabled=1,A7>=Assumptions_MeltdownStartAge,A7<Assumptions_MeltdownTargetAge), MIN(Assumptions_MeltdownAnnual,AL6), 0) | K7: =MIN(MAX(I7,J7),AL6) | L7: =E7+F7+G7+H7+K7 | M7: =IF(C7=1, Assumptions_MonthlyExpenses*12*(1-Assumptions_ExpenseReduction), Assumptions_MonthlyExpenses*12)*D7 | N7: =IF(AND(AP6>0, (A7-Assumptions_CurrentAge)<Assumptions_MortgageYears), IF(Assumptions_MortgageRate=0, AP6/MAX(1,Assumptions_MortgageYears-(A7-Assumptions_CurrentAge)), AP6*Assumptions_MortgageRate*(1+Assumptions_MortgageRate)^MAX(1,Assumptions_MortgageYears-(A7-Assumptions_CurrentAge))/((1+Assumptions_MortgageRate)^MAX(1,Assumptions_MortgageYears-(A7-Assumptions_CurrentAge))-1)), 0) | O7: =IF(AND(Assumptions_ConsumerDebt>0, A7<Assumptions_ConsumerPayoffAge), IF(Assumptions_ConsumerDebtRate=0, Assumptions_ConsumerDebt/MAX(1,Assumptions_ConsumerPayoffAge-Assumptions_CurrentAge-(A7-Assumptions_CurrentAge)), Assumptions_ConsumerDebt*Assumptions_ConsumerDebtRate*(1+Assumptions_ConsumerDebtRate)^MAX(1,Assumptions_ConsumerPayoffAge-Assumptions_CurrentAge-(A7-Assumptions_CurrentAge))/((1+Assumptions_ConsumerDebtRate)^MAX(1,Assumptions_ConsumerPayoffAge-Assumptions_CurrentAge-(A7-Assumptions_CurrentAge))-1)), 0)+IF(AND(Assumptions_OtherDebt>0, A7<Assumptions_OtherPayoffAge), IF(Assumptions_OtherDebtRate=0, Assumptions_OtherDebt/MAX(1,Assumptions_OtherPayoffAge-Assumptions_CurrentAge-(A7-Assumptions_CurrentAge)), Assumptions_OtherDebt*Assumptions_OtherDebtRate*(1+Assumptions_OtherDebtRate)^MAX(1,Assumptions_OtherPayoffAge-Assumptions_CurrentAge-(A7-Assumptions_CurrentAge))/((1+Assumptions_OtherDebtRate)^MAX(1,Assumptions_OtherPayoffAge-Assumptions_CurrentAge-(A7-Assumptions_CurrentAge))-1)), 0) | P7: =M7+N7+O7 | Q7: =IF(L7<=0, 0, MAX(0, SUMPRODUCT(MAX(MIN(L7,FedBracketMax)-FedBracketMin,0)*FedBracketRate) - (FedBasicPersonal + IF(A7>=65, MAX(0, FedAgeAmount - MAX(0, L7-FedAgeThreshold)*FedAgeClawRate), 0) + IF(OR(H7>0, I7>0), FedPensionCredit, 0)) * FedCreditRate)) | R7: =L7-Q7 | S7: =MAX(0,P7-R7) | T7: =MIN(S7,AM6) | U7: =MAX(0,S7-T7) | V7: =MIN(U7,AN6) | W7: =MAX(0,U7-V7) | X7: =INDEX(FedBracketRate,MATCH(L7,FedBracketMin,1))+INDEX(ProvBracketRate,MATCH(L7,ProvBracketMin,1)) | Y7: =IF(W7>0, MIN(IF(X7>=1, W7, W7/(1-X7)), MAX(0,AL6-K7)), 0) | Z7: =K7+Y7 | AA7: =IF(W7>Y7*(1-X7), MIN(MAX(0,W7-Y7*(1-X7)),AO6), 0) | AB7: =MIN(Assumptions_OasMaxAnnual, MAX(0,(E7+F7+G7+H7+Z7-Assumptions_OasClawbackThresh)*Assumptions_OasClawbackRate)) | AC7: =MAX(0,G7-AB7) | AD7: =V7*IF(AN6>0, MAX(0,1-AS6/AN6), 0)*Assumptions_CapGainsRate | AE7: =E7+F7+AC7+H7+Z7+AD7 | AF7: =MAX(0, SUMPRODUCT(MAX(MIN(AE7,FedBracketMax)-FedBracketMin,0)*FedBracketRate) - (FedBasicPersonal + IF(A7>=65, MAX(0, FedAgeAmount - MAX(0, AE7-FedAgeThreshold)*FedAgeClawRate), 0) + IF(OR(H7>0, I7>0), FedPensionCredit, 0)) * FedCreditRate) | AG7: =MAX(0, SUMPRODUCT(MAX(MIN(AE7,ProvBracketMax)-ProvBracketMin,0)*ProvBracketRate) - (ProvBasicPersonal + IF(A7>=65, MAX(0, ProvAgeAmount - MAX(0, AE7-ProvAgeThreshold)*ProvAgeClawRate), 0) + IF(OR(H7>0, I7>0), ProvPensionCredit, 0)) * ProvCreditRate) + MAX(0, (MAX(0, SUMPRODUCT(MAX(MIN(AE7,ProvBracketMax)-ProvBracketMin,0)*ProvBracketRate) - (ProvBasicPersonal + IF(A7>=65, MAX(0, ProvAgeAmount - MAX(0, AE7-ProvAgeThreshold)*ProvAgeClawRate), 0) + IF(OR(H7>0, I7>0), ProvPensionCredit, 0)) * ProvCreditRate)-SurtaxThreshold1)*SurtaxRate1) + MAX(0, (MAX(0, SUMPRODUCT(MAX(MIN(AE7,ProvBracketMax)-ProvBracketMin,0)*ProvBracketRate) - (ProvBasicPersonal + IF(A7>=65, MAX(0, ProvAgeAmount - MAX(0, AE7-ProvAgeThreshold)*ProvAgeClawRate), 0) + IF(OR(H7>0, I7>0), ProvPensionCredit, 0)) * ProvCreditRate)-SurtaxThreshold2)*SurtaxRate2) | AH7: =AF7+AG7 | AI7: =E7+F7+AC7+H7+Z7+T7+V7+AA7-AH7 | AJ7: =AI7-M7-N7-O7 | AK7: =IF(AJ7>0, MIN(AJ7, Assumptions_TfsaAnnualLimit), 0) | AL7: =MAX(0,AL6-Z7)*(1+Assumptions_RealReturn) | AM7: =MAX(0,AM6-T7+AK7)*(1+Assumptions_TfsaReturn) | AN7: =MAX(0,AN6-V7+MAX(0,AJ7-AK7))*(1+Assumptions_NonRegReturn) | AO7: =MAX(0,AO6-AA7)*(1+Assumptions_RealReturn) | AP7: =IF(N7>0, MAX(0, AP6*(1+Assumptions_MortgageRate)-N7), 0) | AQ7: =AL7+AM7+AN7+AO7 | AR7: =AQ7+Assumptions_RealEstateValue-AP7 | AS7: =MAX(0,AS6*MAX(0,AN6-V7)/IF(AN6>0,AN6,1))+MAX(0,AJ7-AK7)
A8: =A7+1 | B8: =2026+(A8-Assumptions_CurrentAge) | C8: =IF(A8>=Assumptions_RetirementAge,1,0) | D8: =(1+Assumptions_Inflation)^(A8-Assumptions_CurrentAge) | E8: =IF(AND(C8=0,Assumptions_StillWorking=1),Assumptions_EmploymentIncome*D8,0) | F8: =IF(A8>=Assumptions_CppStartAge, Assumptions_CppMonthly*12*IF((Assumptions_CppStartAge-65)*12<0, 1+(Assumptions_CppStartAge-65)*12*CppEarlyReduction, 1+(Assumptions_CppStartAge-65)*12*CppLateIncrease)*D8, 0) | G8: =IF(A8>=Assumptions_OasStartAge, Assumptions_OasMonthly*12*(1+MAX(0, MIN(Assumptions_OasStartAge, OasMaxDeferAge)-OasStdStartAge)*12*OasDeferralBonus)*D8, 0) | H8: =IF(AND(Assumptions_PensionType="db",A8>=Assumptions_DbPensionStartAge), IF(Assumptions_DbPensionIndexed=1, Assumptions_DbPensionAnnual*D8, Assumptions_DbPensionAnnual), 0) | I8: =IF(AND(A8>=72,AL7>0), VLOOKUP(MIN(A8,95),RrifRates,2,TRUE)*AL7, 0) | J8: =IF(AND(Assumptions_MeltdownEnabled=1,A8>=Assumptions_MeltdownStartAge,A8<Assumptions_MeltdownTargetAge), MIN(Assumptions_MeltdownAnnual,AL7), 0) | K8: =MIN(MAX(I8,J8),AL7) | L8: =E8+F8+G8+H8+K8 | M8: =IF(C8=1, Assumptions_MonthlyExpenses*12*(1-Assumptions_ExpenseReduction), Assumptions_MonthlyExpenses*12)*D8 | N8: =IF(AND(AP7>0, (A8-Assumptions_CurrentAge)<Assumptions_MortgageYears), IF(Assumptions_MortgageRate=0, AP7/MAX(1,Assumptions_MortgageYears-(A8-Assumptions_CurrentAge)), AP7*Assumptions_MortgageRate*(1+Assumptions_MortgageRate)^MAX(1,Assumptions_MortgageYears-(A8-Assumptions_CurrentAge))/((1+Assumptions_MortgageRate)^MAX(1,Assumptions_MortgageYears-(A8-Assumptions_CurrentAge))-1)), 0) | O8: =IF(AND(Assumptions_ConsumerDebt>0, A8<Assumptions_ConsumerPayoffAge), IF(Assumptions_ConsumerDebtRate=0, Assumptions_ConsumerDebt/MAX(1,Assumptions_ConsumerPayoffAge-Assumptions_CurrentAge-(A8-Assumptions_CurrentAge)), Assumptions_ConsumerDebt*Assumptions_ConsumerDebtRate*(1+Assumptions_ConsumerDebtRate)^MAX(1,Assumptions_ConsumerPayoffAge-Assumptions_CurrentAge-(A8-Assumptions_CurrentAge))/((1+Assumptions_ConsumerDebtRate)^MAX(1,Assumptions_ConsumerPayoffAge-Assumptions_CurrentAge-(A8-Assumptions_CurrentAge))-1)), 0)+IF(AND(Assumptions_OtherDebt>0, A8<Assumptions_OtherPayoffAge), IF(Assumptions_OtherDebtRate=0, Assumptions_OtherDebt/MAX(1,Assumptions_OtherPayoffAge-Assumptions_CurrentAge-(A8-Assumptions_CurrentAge)), Assumptions_OtherDebt*Assumptions_OtherDebtRate*(1+Assumptions_OtherDebtRate)^MAX(1,Assumptions_OtherPayoffAge-Assumptions_CurrentAge-(A8-Assumptions_CurrentAge))/((1+Assumptions_OtherDebtRate)^MAX(1,Assumptions_OtherPayoffAge-Assumptions_CurrentAge-(A8-Assumptions_CurrentAge))-1)), 0) | P8: =M8+N8+O8 | Q8: =IF(L8<=0, 0, MAX(0, SUMPRODUCT(MAX(MIN(L8,FedBracketMax)-FedBracketMin,0)*FedBracketRate) - (FedBasicPersonal + IF(A8>=65, MAX(0, FedAgeAmount - MAX(0, L8-FedAgeThreshold)*FedAgeClawRate), 0) + IF(OR(H8>0, I8>0), FedPensionCredit, 0)) * FedCreditRate)) | R8: =L8-Q8 | S8: =MAX(0,P8-R8) | T8: =MIN(S8,AM7) | U8: =MAX(0,S8-T8) | V8: =MIN(U8,AN7) | W8: =MAX(0,U8-V8) | X8: =INDEX(FedBracketRate,MATCH(L8,FedBracketMin,1))+INDEX(ProvBracketRate,MATCH(L8,ProvBracketMin,1)) | Y8: =IF(W8>0, MIN(IF(X8>=1, W8, W8/(1-X8)), MAX(0,AL7-K8)), 0) | Z8: =K8+Y8 | AA8: =IF(W8>Y8*(1-X8), MIN(MAX(0,W8-Y8*(1-X8)),AO7), 0) | AB8: =MIN(Assumptions_OasMaxAnnual, MAX(0,(E8+F8+G8+H8+Z8-Assumptions_OasClawbackThresh)*Assumptions_OasClawbackRate)) | AC8: =MAX(0,G8-AB8) | AD8: =V8*IF(AN7>0, MAX(0,1-AS7/AN7), 0)*Assumptions_CapGainsRate | AE8: =E8+F8+AC8+H8+Z8+AD8 | AF8: =MAX(0, SUMPRODUCT(MAX(MIN(AE8,FedBracketMax)-FedBracketMin,0)*FedBracketRate) - (FedBasicPersonal + IF(A8>=65, MAX(0, FedAgeAmount - MAX(0, AE8-FedAgeThreshold)*FedAgeClawRate), 0) + IF(OR(H8>0, I8>0), FedPensionCredit, 0)) * FedCreditRate) | AG8: =MAX(0, SUMPRODUCT(MAX(MIN(AE8,ProvBracketMax)-ProvBracketMin,0)*ProvBracketRate) - (ProvBasicPersonal + IF(A8>=65, MAX(0, ProvAgeAmount - MAX(0, AE8-ProvAgeThreshold)*ProvAgeClawRate), 0) + IF(OR(H8>0, I8>0), ProvPensionCredit, 0)) * ProvCreditRate) + MAX(0, (MAX(0, SUMPRODUCT(MAX(MIN(AE8,ProvBracketMax)-ProvBracketMin,0)*ProvBracketRate) - (ProvBasicPersonal + IF(A8>=65, MAX(0, ProvAgeAmount - MAX(0, AE8-ProvAgeThreshold)*ProvAgeClawRate), 0) + IF(OR(H8>0, I8>0), ProvPensionCredit, 0)) * ProvCreditRate)-SurtaxThreshold1)*SurtaxRate1) + MAX(0, (MAX(0, SUMPRODUCT(MAX(MIN(AE8,ProvBracketMax)-ProvBracketMin,0)*ProvBracketRate) - (ProvBasicPersonal + IF(A8>=65, MAX(0, ProvAgeAmount - MAX(0, AE8-ProvAgeThreshold)*ProvAgeClawRate), 0) + IF(OR(H8>0, I8>0), ProvPensionCredit, 0)) * ProvCreditRate)-SurtaxThreshold2)*SurtaxRate2) | AH8: =AF8+AG8 | AI8: =E8+F8+AC8+H8+Z8+T8+V8+AA8-AH8 | AJ8: =AI8-M8-N8-O8 | AK8: =IF(AJ8>0, MIN(AJ8, Assumptions_TfsaAnnualLimit), 0) | AL8: =MAX(0,AL7-Z8)*(1+Assumptions_RealReturn) | AM8: =MAX(0,AM7-T8+AK8)*(1+Assumptions_TfsaReturn) | AN8: =MAX(0,AN7-V8+MAX(0,AJ8-AK8))*(1+Assumptions_NonRegReturn) | AO8: =MAX(0,AO7-AA8)*(1+Assumptions_RealReturn) | AP8: =IF(N8>0, MAX(0, AP7*(1+Assumptions_MortgageRate)-N8), 0) | AQ8: =AL8+AM8+AN8+AO8 | AR8: =AQ8+Assumptions_RealEstateValue-AP8 | AS8: =MAX(0,AS7*MAX(0,AN7-V8)/IF(AN7>0,AN7,1))+MAX(0,AJ8-AK8)
A9: =A8+1 | B9: =2026+(A9-Assumptions_CurrentAge) | C9: =IF(A9>=Assumptions_RetirementAge,1,0) | D9: =(1+Assumptions_Inflation)^(A9-Assumptions_CurrentAge) | E9: =IF(AND(C9=0,Assumptions_StillWorking=1),Assumptions_EmploymentIncome*D9,0) | F9: =IF(A9>=Assumptions_CppStartAge, Assumptions_CppMonthly*12*IF((Assumptions_CppStartAge-65)*12<0, 1+(Assumptions_CppStartAge-65)*12*CppEarlyReduction, 1+(Assumptions_CppStartAge-65)*12*CppLateIncrease)*D9, 0) | G9: =IF(A9>=Assumptions_OasStartAge, Assumptions_OasMonthly*12*(1+MAX(0, MIN(Assumptions_OasStartAge, OasMaxDeferAge)-OasStdStartAge)*12*OasDeferralBonus)*D9, 0) | H9: =IF(AND(Assumptions_PensionType="db",A9>=Assumptions_DbPensionStartAge), IF(Assumptions_DbPensionIndexed=1, Assumptions_DbPensionAnnual*D9, Assumptions_DbPensionAnnual), 0) | I9: =IF(AND(A9>=72,AL8>0), VLOOKUP(MIN(A9,95),RrifRates,2,TRUE)*AL8, 0) | J9: =IF(AND(Assumptions_MeltdownEnabled=1,A9>=Assumptions_MeltdownStartAge,A9<Assumptions_MeltdownTargetAge), MIN(Assumptions_MeltdownAnnual,AL8), 0) | K9: =MIN(MAX(I9,J9),AL8) | L9: =E9+F9+G9+H9+K9 | M9: =IF(C9=1, Assumptions_MonthlyExpenses*12*(1-Assumptions_ExpenseReduction), Assumptions_MonthlyExpenses*12)*D9 | N9: =IF(AND(AP8>0, (A9-Assumptions_CurrentAge)<Assumptions_MortgageYears), IF(Assumptions_MortgageRate=0, AP8/MAX(1,Assumptions_MortgageYears-(A9-Assumptions_CurrentAge)), AP8*Assumptions_MortgageRate*(1+Assumptions_MortgageRate)^MAX(1,Assumptions_MortgageYears-(A9-Assumptions_CurrentAge))/((1+Assumptions_MortgageRate)^MAX(1,Assumptions_MortgageYears-(A9-Assumptions_CurrentAge))-1)), 0) | O9: =IF(AND(Assumptions_ConsumerDebt>0, A9<Assumptions_ConsumerPayoffAge), IF(Assumptions_ConsumerDebtRate=0, Assumptions_ConsumerDebt/MAX(1,Assumptions_ConsumerPayoffAge-Assumptions_CurrentAge-(A9-Assumptions_CurrentAge)), Assumptions_ConsumerDebt*Assumptions_ConsumerDebtRate*(1+Assumptions_ConsumerDebtRate)^MAX(1,Assumptions_ConsumerPayoffAge-Assumptions_CurrentAge-(A9-Assumptions_CurrentAge))/((1+Assumptions_ConsumerDebtRate)^MAX(1,Assumptions_ConsumerPayoffAge-Assumptions_CurrentAge-(A9-Assumptions_CurrentAge))-1)), 0)+IF(AND(Assumptions_OtherDebt>0, A9<Assumptions_OtherPayoffAge), IF(Assumptions_OtherDebtRate=0, Assumptions_OtherDebt/MAX(1,Assumptions_OtherPayoffAge-Assumptions_CurrentAge-(A9-Assumptions_CurrentAge)), Assumptions_OtherDebt*Assumptions_OtherDebtRate*(1+Assumptions_OtherDebtRate)^MAX(1,Assumptions_OtherPayoffAge-Assumptions_CurrentAge-(A9-Assumptions_CurrentAge))/((1+Assumptions_OtherDebtRate)^MAX(1,Assumptions_OtherPayoffAge-Assumptions_CurrentAge-(A9-Assumptions_CurrentAge))-1)), 0) | P9: =M9+N9+O9 | Q9: =IF(L9<=0, 0, MAX(0, SUMPRODUCT(MAX(MIN(L9,FedBracketMax)-FedBracketMin,0)*FedBracketRate) - (FedBasicPersonal + IF(A9>=65, MAX(0, FedAgeAmount - MAX(0, L9-FedAgeThreshold)*FedAgeClawRate), 0) + IF(OR(H9>0, I9>0), FedPensionCredit, 0)) * FedCreditRate)) | R9: =L9-Q9 | S9: =MAX(0,P9-R9) | T9: =MIN(S9,AM8) | U9: =MAX(0,S9-T9) | V9: =MIN(U9,AN8) | W9: =MAX(0,U9-V9) | X9: =INDEX(FedBracketRate,MATCH(L9,FedBracketMin,1))+INDEX(ProvBracketRate,MATCH(L9,ProvBracketMin,1)) | Y9: =IF(W9>0, MIN(IF(X9>=1, W9, W9/(1-X9)), MAX(0,AL8-K9)), 0) | Z9: =K9+Y9 | AA9: =IF(W9>Y9*(1-X9), MIN(MAX(0,W9-Y9*(1-X9)),AO8), 0) | AB9: =MIN(Assumptions_OasMaxAnnual, MAX(0,(E9+F9+G9+H9+Z9-Assumptions_OasClawbackThresh)*Assumptions_OasClawbackRate)) | AC9: =MAX(0,G9-AB9) | AD9: =V9*IF(AN8>0, MAX(0,1-AS8/AN8), 0)*Assumptions_CapGainsRate | AE9: =E9+F9+AC9+H9+Z9+AD9 | AF9: =MAX(0, SUMPRODUCT(MAX(MIN(AE9,FedBracketMax)-FedBracketMin,0)*FedBracketRate) - (FedBasicPersonal + IF(A9>=65, MAX(0, FedAgeAmount - MAX(0, AE9-FedAgeThreshold)*FedAgeClawRate), 0) + IF(OR(H9>0, I9>0), FedPensionCredit, 0)) * FedCreditRate) | AG9: =MAX(0, SUMPRODUCT(MAX(MIN(AE9,ProvBracketMax)-ProvBracketMin,0)*ProvBracketRate) - (ProvBasicPersonal + IF(A9>=65, MAX(0, ProvAgeAmount - MAX(0, AE9-ProvAgeThreshold)*ProvAgeClawRate), 0) + IF(OR(H9>0, I9>0), ProvPensionCredit, 0)) * ProvCreditRate) + MAX(0, (MAX(0, SUMPRODUCT(MAX(MIN(AE9,ProvBracketMax)-ProvBracketMin,0)*ProvBracketRate) - (ProvBasicPersonal + IF(A9>=65, MAX(0, ProvAgeAmount - MAX(0, AE9-ProvAgeThreshold)*ProvAgeClawRate), 0) + IF(OR(H9>0, I9>0), ProvPensionCredit, 0)) * ProvCreditRate)-SurtaxThreshold1)*SurtaxRate1) + MAX(0, (MAX(0, SUMPRODUCT(MAX(MIN(AE9,ProvBracketMax)-ProvBracketMin,0)*ProvBracketRate) - (ProvBasicPersonal + IF(A9>=65, MAX(0, ProvAgeAmount - MAX(0, AE9-ProvAgeThreshold)*ProvAgeClawRate), 0) + IF(OR(H9>0, I9>0), ProvPensionCredit, 0)) * ProvCreditRate)-SurtaxThreshold2)*SurtaxRate2) | AH9: =AF9+AG9 | AI9: =E9+F9+AC9+H9+Z9+T9+V9+AA9-AH9 | AJ9: =AI9-M9-N9-O9 | AK9: =IF(AJ9>0, MIN(AJ9, Assumptions_TfsaAnnualLimit), 0) | AL9: =MAX(0,AL8-Z9)*(1+Assumptions_RealReturn) | AM9: =MAX(0,AM8-T9+AK9)*(1+Assumptions_TfsaReturn) | AN9: =MAX(0,AN8-V9+MAX(0,AJ9-AK9))*(1+Assumptions_NonRegReturn) | AO9: =MAX(0,AO8-AA9)*(1+Assumptions_RealReturn) | AP9: =IF(N9>0, MAX(0, AP8*(1+Assumptions_MortgageRate)-N9), 0) | AQ9: =AL9+AM9+AN9+AO9 | AR9: =AQ9+Assumptions_RealEstateValue-AP9 | AS9: =MAX(0,AS8*MAX(0,AN8-V9)/IF(AN8>0,AN8,1))+MAX(0,AJ9-AK9)
A10: =A9+1 | B10: =2026+(A10-Assumptions_CurrentAge) | C10: =IF(A10>=Assumptions_RetirementAge,1,0) | D10: =(1+Assumptions_Inflation)^(A10-Assumptions_CurrentAge) | E10: =IF(AND(C10=0,Assumptions_StillWorking=1),Assumptions_EmploymentIncome*D10,0) | F10: =IF(A10>=Assumptions_CppStartAge, Assumptions_CppMonthly*12*IF((Assumptions_CppStartAge-65)*12<0, 1+(Assumptions_CppStartAge-65)*12*CppEarlyReduction, 1+(Assumptions_CppStartAge-65)*12*CppLateIncrease)*D10, 0) | G10: =IF(A10>=Assumptions_OasStartAge, Assumptions_OasMonthly*12*(1+MAX(0, MIN(Assumptions_OasStartAge, OasMaxDeferAge)-OasStdStartAge)*12*OasDeferralBonus)*D10, 0) | H10: =IF(AND(Assumptions_PensionType="db",A10>=Assumptions_DbPensionStartAge), IF(Assumptions_DbPensionIndexed=1, Assumptions_DbPensionAnnual*D10, Assumptions_DbPensionAnnual), 0) | I10: =IF(AND(A10>=72,AL9>0), VLOOKUP(MIN(A10,95),RrifRates,2,TRUE)*AL9, 0) | J10: =IF(AND(Assumptions_MeltdownEnabled=1,A10>=Assumptions_MeltdownStartAge,A10<Assumptions_MeltdownTargetAge), MIN(Assumptions_MeltdownAnnual,AL9), 0) | K10: =MIN(MAX(I10,J10),AL9) | L10: =E10+F10+G10+H10+K10 | M10: =IF(C10=1, Assumptions_MonthlyExpenses*12*(1-Assumptions_ExpenseReduction), Assumptions_MonthlyExpenses*12)*D10 | N10: =IF(AND(AP9>0, (A10-Assumptions_CurrentAge)<Assumptions_MortgageYears), IF(Assumptions_MortgageRate=0, AP9/MAX(1,Assumptions_MortgageYears-(A10-Assumptions_CurrentAge)), AP9*Assumptions_MortgageRate*(1+Assumptions_MortgageRate)^MAX(1,Assumptions_MortgageYears-(A10-Assumptions_CurrentAge))/((1+Assumptions_MortgageRate)^MAX(1,Assumptions_MortgageYears-(A10-Assumptions_CurrentAge))-1)), 0) | O10: =IF(AND(Assumptions_ConsumerDebt>0, A10<Assumptions_ConsumerPayoffAge), IF(Assumptions_ConsumerDebtRate=0, Assumptions_ConsumerDebt/MAX(1,Assumptions_ConsumerPayoffAge-Assumptions_CurrentAge-(A10-Assumptions_CurrentAge)), Assumptions_ConsumerDebt*Assumptions_ConsumerDebtRate*(1+Assumptions_ConsumerDebtRate)^MAX(1,Assumptions_ConsumerPayoffAge-Assumptions_CurrentAge-(A10-Assumptions_CurrentAge))/((1+Assumptions_ConsumerDebtRate)^MAX(1,Assumptions_ConsumerPayoffAge-Assumptions_CurrentAge-(A10-Assumptions_CurrentAge))-1)), 0)+IF(AND(Assumptions_OtherDebt>0, A10<Assumptions_OtherPayoffAge), IF(Assumptions_OtherDebtRate=0, Assumptions_OtherDebt/MAX(1,Assumptions_OtherPayoffAge-Assumptions_CurrentAge-(A10-Assumptions_CurrentAge)), Assumptions_OtherDebt*Assumptions_OtherDebtRate*(1+Assumptions_OtherDebtRate)^MAX(1,Assumptions_OtherPayoffAge-Assumptions_CurrentAge-(A10-Assumptions_CurrentAge))/((1+Assumptions_OtherDebtRate)^MAX(1,Assumptions_OtherPayoffAge-Assumptions_CurrentAge-(A10-Assumptions_CurrentAge))-1)), 0) | P10: =M10+N10+O10 | Q10: =IF(L10<=0, 0, MAX(0, SUMPRODUCT(MAX(MIN(L10,FedBracketMax)-FedBracketMin,0)*FedBracketRate) - (FedBasicPersonal + IF(A10>=65, MAX(0, FedAgeAmount - MAX(0, L10-FedAgeThreshold)*FedAgeClawRate), 0) + IF(OR(H10>0, I10>0), FedPensionCredit, 0)) * FedCreditRate)) | R10: =L10-Q10 | S10: =MAX(0,P10-R10) | T10: =MIN(S10,AM9) | U10: =MAX(0,S10-T10) | V10: =MIN(U10,AN9) | W10: =MAX(0,U10-V10) | X10: =INDEX(FedBracketRate,MATCH(L10,FedBracketMin,1))+INDEX(ProvBracketRate,MATCH(L10,ProvBracketMin,1)) | Y10: =IF(W10>0, MIN(IF(X10>=1, W10, W10/(1-X10)), MAX(0,AL9-K10)), 0) | Z10: =K10+Y10 | AA10: =IF(W10>Y10*(1-X10), MIN(MAX(0,W10-Y10*(1-X10)),AO9), 0) | AB10: =MIN(Assumptions_OasMaxAnnual, MAX(0,(E10+F10+G10+H10+Z10-Assumptions_OasClawbackThresh)*Assumptions_OasClawbackRate)) | AC10: =MAX(0,G10-AB10) | AD10: =V10*IF(AN9>0, MAX(0,1-AS9/AN9), 0)*Assumptions_CapGainsRate | AE10: =E10+F10+AC10+H10+Z10+AD10 | AF10: =MAX(0, SUMPRODUCT(MAX(MIN(AE10,FedBracketMax)-FedBracketMin,0)*FedBracketRate) - (FedBasicPersonal + IF(A10>=65, MAX(0, FedAgeAmount - MAX(0, AE10-FedAgeThreshold)*FedAgeClawRate), 0) + IF(OR(H10>0, I10>0), FedPensionCredit, 0)) * FedCreditRate) | AG10: =MAX(0, SUMPRODUCT(MAX(MIN(AE10,ProvBracketMax)-ProvBracketMin,0)*ProvBracketRate) - (ProvBasicPersonal + IF(A10>=65, MAX(0, ProvAgeAmount - MAX(0, AE10-ProvAgeThreshold)*ProvAgeClawRate), 0) + IF(OR(H10>0, I10>0), ProvPensionCredit, 0)) * ProvCreditRate) + MAX(0, (MAX(0, SUMPRODUCT(MAX(MIN(AE10,ProvBracketMax)-ProvBracketMin,0)*ProvBracketRate) - (ProvBasicPersonal + IF(A10>=65, MAX(0, ProvAgeAmount - MAX(0, AE10-ProvAgeThreshold)*ProvAgeClawRate), 0) + IF(OR(H10>0, I10>0), ProvPensionCredit, 0)) * ProvCreditRate)-SurtaxThreshold1)*SurtaxRate1) + MAX(0, (MAX(0, SUMPRODUCT(MAX(MIN(AE10,ProvBracketMax)-ProvBracketMin,0)*ProvBracketRate) - (ProvBasicPersonal + IF(A10>=65, MAX(0, ProvAgeAmount - MAX(0, AE10-ProvAgeThreshold)*ProvAgeClawRate), 0) + IF(OR(H10>0, I10>0), ProvPensionCredit, 0)) * ProvCreditRate)-SurtaxThreshold2)*SurtaxRate2) | AH10: =AF10+AG10 | AI10: =E10+F10+AC10+H10+Z10+T10+V10+AA10-AH10 | AJ10: =AI10-M10-N10-O10 | AK10: =IF(AJ10>0, MIN(AJ10, Assumptions_TfsaAnnualLimit), 0) | AL10: =MAX(0,AL9-Z10)*(1+Assumptions_RealReturn) | AM10: =MAX(0,AM9-T10+AK10)*(1+Assumptions_TfsaReturn) | AN10: =MAX(0,AN9-V10+MAX(0,AJ10-AK10))*(1+Assumptions_NonRegReturn) | AO10: =MAX(0,AO9-AA10)*(1+Assumptions_RealReturn) | AP10: =IF(N10>0, MAX(0, AP9*(1+Assumptions_MortgageRate)-N10), 0) | AQ10: =AL10+AM10+AN10+AO10 | AR10: =AQ10+Assumptions_RealEstateValue-AP10 | AS10: =MAX(0,AS9*MAX(0,AN9-V10)/IF(AN9>0,AN9,1))+MAX(0,AJ10-AK10)
A11: =A10+1 | B11: =2026+(A11-Assumptions_CurrentAge) | C11: =IF(A11>=Assumptions_RetirementAge,1,0) | D11: =(1+Assumptions_Inflation)^(A11-Assumptions_CurrentAge) | E11: =IF(AND(C11=0,Assumptions_StillWorking=1),Assumptions_EmploymentIncome*D11,0) | F11: =IF(A11>=Assumptions_CppStartAge, Assumptions_CppMonthly*12*IF((Assumptions_CppStartAge-65)*12<0, 1+(Assumptions_CppStartAge-65)*12*CppEarlyReduction, 1+(Assumptions_CppStartAge-65)*12*CppLateIncrease)*D11, 0) | G11: =IF(A11>=Assumptions_OasStartAge, Assumptions_OasMonthly*12*(1+MAX(0, MIN(Assumptions_OasStartAge, OasMaxDeferAge)-OasStdStartAge)*12*OasDeferralBonus)*D11, 0) | H11: =IF(AND(Assumptions_PensionType="db",A11>=Assumptions_DbPensionStartAge), IF(Assumptions_DbPensionIndexed=1, Assumptions_DbPensionAnnual*D11, Assumptions_DbPensionAnnual), 0) | I11: =IF(AND(A11>=72,AL10>0), VLOOKUP(MIN(A11,95),RrifRates,2,TRUE)*AL10, 0) | J11: =IF(AND(Assumptions_MeltdownEnabled=1,A11>=Assumptions_MeltdownStartAge,A11<Assumptions_MeltdownTargetAge), MIN(Assumptions_MeltdownAnnual,AL10), 0) | K11: =MIN(MAX(I11,J11),AL10) | L11: =E11+F11+G11+H11+K11 | M11: =IF(C11=1, Assumptions_MonthlyExpenses*12*(1-Assumptions_ExpenseReduction), Assumptions_MonthlyExpenses*12)*D11 | N11: =IF(AND(AP10>0, (A11-Assumptions_CurrentAge)<Assumptions_MortgageYears), IF(Assumptions_MortgageRate=0, AP10/MAX(1,Assumptions_MortgageYears-(A11-Assumptions_CurrentAge)), AP10*Assumptions_MortgageRate*(1+Assumptions_MortgageRate)^MAX(1,Assumptions_MortgageYears-(A11-Assumptions_CurrentAge))/((1+Assumptions_MortgageRate)^MAX(1,Assumptions_MortgageYears-(A11-Assumptions_CurrentAge))-1)), 0) | O11: =IF(AND(Assumptions_ConsumerDebt>0, A11<Assumptions_ConsumerPayoffAge), IF(Assumptions_ConsumerDebtRate=0, Assumptions_ConsumerDebt/MAX(1,Assumptions_ConsumerPayoffAge-Assumptions_CurrentAge-(A11-Assumptions_CurrentAge)), Assumptions_ConsumerDebt*Assumptions_ConsumerDebtRate*(1+Assumptions_ConsumerDebtRate)^MAX(1,Assumptions_ConsumerPayoffAge-Assumptions_CurrentAge-(A11-Assumptions_CurrentAge))/((1+Assumptions_ConsumerDebtRate)^MAX(1,Assumptions_ConsumerPayoffAge-Assumptions_CurrentAge-(A11-Assumptions_CurrentAge))-1)), 0)+IF(AND(Assumptions_OtherDebt>0, A11<Assumptions_OtherPayoffAge), IF(Assumptions_OtherDebtRate=0, Assumptions_OtherDebt/MAX(1,Assumptions_OtherPayoffAge-Assumptions_CurrentAge-(A11-Assumptions_CurrentAge)), Assumptions_OtherDebt*Assumptions_OtherDebtRate*(1+Assumptions_OtherDebtRate)^MAX(1,Assumptions_OtherPayoffAge-Assumptions_CurrentAge-(A11-Assumptions_CurrentAge))/((1+Assumptions_OtherDebtRate)^MAX(1,Assumptions_OtherPayoffAge-Assumptions_CurrentAge-(A11-Assumptions_CurrentAge))-1)), 0) | P11: =M11+N11+O11 | Q11: =IF(L11<=0, 0, MAX(0, SUMPRODUCT(MAX(MIN(L11,FedBracketMax)-FedBracketMin,0)*FedBracketRate) - (FedBasicPersonal + IF(A11>=65, MAX(0, FedAgeAmount - MAX(0, L11-FedAgeThreshold)*FedAgeClawRate), 0) + IF(OR(H11>0, I11>0), FedPensionCredit, 0)) * FedCreditRate)) | R11: =L11-Q11 | S11: =MAX(0,P11-R11) | T11: =MIN(S11,AM10) | U11: =MAX(0,S11-T11) | V11: =MIN(U11,AN10) | W11: =MAX(0,U11-V11) | X11: =INDEX(FedBracketRate,MATCH(L11,FedBracketMin,1))+INDEX(ProvBracketRate,MATCH(L11,ProvBracketMin,1)) | Y11: =IF(W11>0, MIN(IF(X11>=1, W11, W11/(1-X11)), MAX(0,AL10-K11)), 0) | Z11: =K11+Y11 | AA11: =IF(W11>Y11*(1-X11), MIN(MAX(0,W11-Y11*(1-X11)),AO10), 0) | AB11: =MIN(Assumptions_OasMaxAnnual, MAX(0,(E11+F11+G11+H11+Z11-Assumptions_OasClawbackThresh)*Assumptions_OasClawbackRate)) | AC11: =MAX(0,G11-AB11) | AD11: =V11*IF(AN10>0, MAX(0,1-AS10/AN10), 0)*Assumptions_CapGainsRate | AE11: =E11+F11+AC11+H11+Z11+AD11 | AF11: =MAX(0, SUMPRODUCT(MAX(MIN(AE11,FedBracketMax)-FedBracketMin,0)*FedBracketRate) - (FedBasicPersonal + IF(A11>=65, MAX(0, FedAgeAmount - MAX(0, AE11-FedAgeThreshold)*FedAgeClawRate), 0) + IF(OR(H11>0, I11>0), FedPensionCredit, 0)) * FedCreditRate) | AG11: =MAX(0, SUMPRODUCT(MAX(MIN(AE11,ProvBracketMax)-ProvBracketMin,0)*ProvBracketRate) - (ProvBasicPersonal + IF(A11>=65, MAX(0, ProvAgeAmount - MAX(0, AE11-ProvAgeThreshold)*ProvAgeClawRate), 0) + IF(OR(H11>0, I11>0), ProvPensionCredit, 0)) * ProvCreditRate) + MAX(0, (MAX(0, SUMPRODUCT(MAX(MIN(AE11,ProvBracketMax)-ProvBracketMin,0)*ProvBracketRate) - (ProvBasicPersonal + IF(A11>=65, MAX(0, ProvAgeAmount - MAX(0, AE11-ProvAgeThreshold)*ProvAgeClawRate), 0) + IF(OR(H11>0, I11>0), ProvPensionCredit, 0)) * ProvCreditRate)-SurtaxThreshold1)*SurtaxRate1) + MAX(0, (MAX(0, SUMPRODUCT(MAX(MIN(AE11,ProvBracketMax)-ProvBracketMin,0)*ProvBracketRate) - (ProvBasicPersonal + IF(A11>=65, MAX(0, ProvAgeAmount - MAX(0, AE11-ProvAgeThreshold)*ProvAgeClawRate), 0) + IF(OR(H11>0, I11>0), ProvPensionCredit, 0)) * ProvCreditRate)-SurtaxThreshold2)*SurtaxRate2) | AH11: =AF11+AG11 | AI11: =E11+F11+AC11+H11+Z11+T11+V11+AA11-AH11 | AJ11: =AI11-M11-N11-O11 | AK11: =IF(AJ11>0, MIN(AJ11, Assumptions_TfsaAnnualLimit), 0) | AL11: =MAX(0,AL10-Z11)*(1+Assumptions_RealReturn) | AM11: =MAX(0,AM10-T11+AK11)*(1+Assumptions_TfsaReturn) | AN11: =MAX(0,AN10-V11+MAX(0,AJ11-AK11))*(1+Assumptions_NonRegReturn) | AO11: =MAX(0,AO10-AA11)*(1+Assumptions_RealReturn) | AP11: =IF(N11>0, MAX(0, AP10*(1+Assumptions_MortgageRate)-N11), 0) | AQ11: =AL11+AM11+AN11+AO11 | AR11: =AQ11+Assumptions_RealEstateValue-AP11 | AS11: =MAX(0,AS10*MAX(0,AN10-V11)/IF(AN10>0,AN10,1))+MAX(0,AJ11-AK11)
A12: =A11+1 | B12: =2026+(A12-Assumptions_CurrentAge) | C12: =IF(A12>=Assumptions_RetirementAge,1,0) | D12: =(1+Assumptions_Inflation)^(A12-Assumptions_CurrentAge) | E12: =IF(AND(C12=0,Assumptions_StillWorking=1),Assumptions_EmploymentIncome*D12,0) | F12: =IF(A12>=Assumptions_CppStartAge, Assumptions_CppMonthly*12*IF((Assumptions_CppStartAge-65)*12<0, 1+(Assumptions_CppStartAge-65)*12*CppEarlyReduction, 1+(Assumptions_CppStartAge-65)*12*CppLateIncrease)*D12, 0) | G12: =IF(A12>=Assumptions_OasStartAge, Assumptions_OasMonthly*12*(1+MAX(0, MIN(Assumptions_OasStartAge, OasMaxDeferAge)-OasStdStartAge)*12*OasDeferralBonus)*D12, 0) | H12: =IF(AND(Assumptions_PensionType="db",A12>=Assumptions_DbPensionStartAge), IF(Assumptions_DbPensionIndexed=1, Assumptions_DbPensionAnnual*D12, Assumptions_DbPensionAnnual), 0) | I12: =IF(AND(A12>=72,AL11>0), VLOOKUP(MIN(A12,95),RrifRates,2,TRUE)*AL11, 0) | J12: =IF(AND(Assumptions_MeltdownEnabled=1,A12>=Assumptions_MeltdownStartAge,A12<Assumptions_MeltdownTargetAge), MIN(Assumptions_MeltdownAnnual,AL11), 0) | K12: =MIN(MAX(I12,J12),AL11) | L12: =E12+F12+G12+H12+K12 | M12: =IF(C12=1, Assumptions_MonthlyExpenses*12*(1-Assumptions_ExpenseReduction), Assumptions_MonthlyExpenses*12)*D12 | N12: =IF(AND(AP11>0, (A12-Assumptions_CurrentAge)<Assumptions_MortgageYears), IF(Assumptions_MortgageRate=0, AP11/MAX(1,Assumptions_MortgageYears-(A12-Assumptions_CurrentAge)), AP11*Assumptions_MortgageRate*(1+Assumptions_MortgageRate)^MAX(1,Assumptions_MortgageYears-(A12-Assumptions_CurrentAge))/((1+Assumptions_MortgageRate)^MAX(1,Assumptions_MortgageYears-(A12-Assumptions_CurrentAge))-1)), 0) | O12: =IF(AND(Assumptions_ConsumerDebt>0, A12<Assumptions_ConsumerPayoffAge), IF(Assumptions_ConsumerDebtRate=0, Assumptions_ConsumerDebt/MAX(1,Assumptions_ConsumerPayoffAge-Assumptions_CurrentAge-(A12-Assumptions_CurrentAge)), Assumptions_ConsumerDebt*Assumptions_ConsumerDebtRate*(1+Assumptions_ConsumerDebtRate)^MAX(1,Assumptions_ConsumerPayoffAge-Assumptions_CurrentAge-(A12-Assumptions_CurrentAge))/((1+Assumptions_ConsumerDebtRate)^MAX(1,Assumptions_ConsumerPayoffAge-Assumptions_CurrentAge-(A12-Assumptions_CurrentAge))-1)), 0)+IF(AND(Assumptions_OtherDebt>0, A12<Assumptions_OtherPayoffAge), IF(Assumptions_OtherDebtRate=0, Assumptions_OtherDebt/MAX(1,Assumptions_OtherPayoffAge-Assumptions_CurrentAge-(A12-Assumptions_CurrentAge)), Assumptions_OtherDebt*Assumptions_OtherDebtRate*(1+Assumptions_OtherDebtRate)^MAX(1,Assumptions_OtherPayoffAge-Assumptions_CurrentAge-(A12-Assumptions_CurrentAge))/((1+Assumptions_OtherDebtRate)^MAX(1,Assumptions_OtherPayoffAge-Assumptions_CurrentAge-(A12-Assumptions_CurrentAge))-1)), 0) | P12: =M12+N12+O12 | Q12: =IF(L12<=0, 0, MAX(0, SUMPRODUCT(MAX(MIN(L12,FedBracketMax)-FedBracketMin,0)*FedBracketRate) - (FedBasicPersonal + IF(A12>=65, MAX(0, FedAgeAmount - MAX(0, L12-FedAgeThreshold)*FedAgeClawRate), 0) + IF(OR(H12>0, I12>0), FedPensionCredit, 0)) * FedCreditRate)) | R12: =L12-Q12 | S12: =MAX(0,P12-R12) | T12: =MIN(S12,AM11) | U12: =MAX(0,S12-T12) | V12: =MIN(U12,AN11) | W12: =MAX(0,U12-V12) | X12: =INDEX(FedBracketRate,MATCH(L12,FedBracketMin,1))+INDEX(ProvBracketRate,MATCH(L12,ProvBracketMin,1)) | Y12: =IF(W12>0, MIN(IF(X12>=1, W12, W12/(1-X12)), MAX(0,AL11-K12)), 0) | Z12: =K12+Y12 | AA12: =IF(W12>Y12*(1-X12), MIN(MAX(0,W12-Y12*(1-X12)),AO11), 0) | AB12: =MIN(Assumptions_OasMaxAnnual, MAX(0,(E12+F12+G12+H12+Z12-Assumptions_OasClawbackThresh)*Assumptions_OasClawbackRate)) | AC12: =MAX(0,G12-AB12) | AD12: =V12*IF(AN11>0, MAX(0,1-AS11/AN11), 0)*Assumptions_CapGainsRate | AE12: =E12+F12+AC12+H12+Z12+AD12 | AF12: =MAX(0, SUMPRODUCT(MAX(MIN(AE12,FedBracketMax)-FedBracketMin,0)*FedBracketRate) - (FedBasicPersonal + IF(A12>=65, MAX(0, FedAgeAmount - MAX(0, AE12-FedAgeThreshold)*FedAgeClawRate), 0) + IF(OR(H12>0, I12>0), FedPensionCredit, 0)) * FedCreditRate) | AG12: =MAX(0, SUMPRODUCT(MAX(MIN(AE12,ProvBracketMax)-ProvBracketMin,0)*ProvBracketRate) - (ProvBasicPersonal + IF(A12>=65, MAX(0, ProvAgeAmount - MAX(0, AE12-ProvAgeThreshold)*ProvAgeClawRate), 0) + IF(OR(H12>0, I12>0), ProvPensionCredit, 0)) * ProvCreditRate) + MAX(0, (MAX(0, SUMPRODUCT(MAX(MIN(AE12,ProvBracketMax)-ProvBracketMin,0)*ProvBracketRate) - (ProvBasicPersonal + IF(A12>=65, MAX(0, ProvAgeAmount - MAX(0, AE12-ProvAgeThreshold)*ProvAgeClawRate), 0) + IF(OR(H12>0, I12>0), ProvPensionCredit, 0)) * ProvCreditRate)-SurtaxThreshold1)*SurtaxRate1) + MAX(0, (MAX(0, SUMPRODUCT(MAX(MIN(AE12,ProvBracketMax)-ProvBracketMin,0)*ProvBracketRate) - (ProvBasicPersonal + IF(A12>=65, MAX(0, ProvAgeAmount - MAX(0, AE12-ProvAgeThreshold)*ProvAgeClawRate), 0) + IF(OR(H12>0, I12>0), ProvPensionCredit, 0)) * ProvCreditRate)-SurtaxThreshold2)*SurtaxRate2) | AH12: =AF12+AG12 | AI12: =E12+F12+AC12+H12+Z12+T12+V12+AA12-AH12 | AJ12: =AI12-M12-N12-O12 | AK12: =IF(AJ12>0, MIN(AJ12, Assumptions_TfsaAnnualLimit), 0) | AL12: =MAX(0,AL11-Z12)*(1+Assumptions_RealReturn) | AM12: =MAX(0,AM11-T12+AK12)*(1+Assumptions_TfsaReturn) | AN12: =MAX(0,AN11-V12+MAX(0,AJ12-AK12))*(1+Assumptions_NonRegReturn) | AO12: =MAX(0,AO11-AA12)*(1+Assumptions_RealReturn) | AP12: =IF(N12>0, MAX(0, AP11*(1+Assumptions_MortgageRate)-N12), 0) | AQ12: =AL12+AM12+AN12+AO12 | AR12: =AQ12+Assumptions_RealEstateValue-AP12 | AS12: =MAX(0,AS11*MAX(0,AN11-V12)/IF(AN11>0,AN11,1))+MAX(0,AJ12-AK12)
A13: =A12+1 | B13: =2026+(A13-Assumptions_CurrentAge) | C13: =IF(A13>=Assumptions_RetirementAge,1,0) | D13: =(1+Assumptions_Inflation)^(A13-Assumptions_CurrentAge) | E13: =IF(AND(C13=0,Assumptions_StillWorking=1),Assumptions_EmploymentIncome*D13,0) | F13: =IF(A13>=Assumptions_CppStartAge, Assumptions_CppMonthly*12*IF((Assumptions_CppStartAge-65)*12<0, 1+(Assumptions_CppStartAge-65)*12*CppEarlyReduction, 1+(Assumptions_CppStartAge-65)*12*CppLateIncrease)*D13, 0) | G13: =IF(A13>=Assumptions_OasStartAge, Assumptions_OasMonthly*12*(1+MAX(0, MIN(Assumptions_OasStartAge, OasMaxDeferAge)-OasStdStartAge)*12*OasDeferralBonus)*D13, 0) | H13: =IF(AND(Assumptions_PensionType="db",A13>=Assumptions_DbPensionStartAge), IF(Assumptions_DbPensionIndexed=1, Assumptions_DbPensionAnnual*D13, Assumptions_DbPensionAnnual), 0) | I13: =IF(AND(A13>=72,AL12>0), VLOOKUP(MIN(A13,95),RrifRates,2,TRUE)*AL12, 0) | J13: =IF(AND(Assumptions_MeltdownEnabled=1,A13>=Assumptions_MeltdownStartAge,A13<Assumptions_MeltdownTargetAge), MIN(Assumptions_MeltdownAnnual,AL12), 0) | K13: =MIN(MAX(I13,J13),AL12) | L13: =E13+F13+G13+H13+K13 | M13: =IF(C13=1, Assumptions_MonthlyExpenses*12*(1-Assumptions_ExpenseReduction), Assumptions_MonthlyExpenses*12)*D13 | N13: =IF(AND(AP12>0, (A13-Assumptions_CurrentAge)<Assumptions_MortgageYears), IF(Assumptions_MortgageRate=0, AP12/MAX(1,Assumptions_MortgageYears-(A13-Assumptions_CurrentAge)), AP12*Assumptions_MortgageRate*(1+Assumptions_MortgageRate)^MAX(1,Assumptions_MortgageYears-(A13-Assumptions_CurrentAge))/((1+Assumptions_MortgageRate)^MAX(1,Assumptions_MortgageYears-(A13-Assumptions_CurrentAge))-1)), 0) | O13: =IF(AND(Assumptions_ConsumerDebt>0, A13<Assumptions_ConsumerPayoffAge), IF(Assumptions_ConsumerDebtRate=0, Assumptions_ConsumerDebt/MAX(1,Assumptions_ConsumerPayoffAge-Assumptions_CurrentAge-(A13-Assumptions_CurrentAge)), Assumptions_ConsumerDebt*Assumptions_ConsumerDebtRate*(1+Assumptions_ConsumerDebtRate)^MAX(1,Assumptions_ConsumerPayoffAge-Assumptions_CurrentAge-(A13-Assumptions_CurrentAge))/((1+Assumptions_ConsumerDebtRate)^MAX(1,Assumptions_ConsumerPayoffAge-Assumptions_CurrentAge-(A13-Assumptions_CurrentAge))-1)), 0)+IF(AND(Assumptions_OtherDebt>0, A13<Assumptions_OtherPayoffAge), IF(Assumptions_OtherDebtRate=0, Assumptions_OtherDebt/MAX(1,Assumptions_OtherPayoffAge-Assumptions_CurrentAge-(A13-Assumptions_CurrentAge)), Assumptions_OtherDebt*Assumptions_OtherDebtRate*(1+Assumptions_OtherDebtRate)^MAX(1,Assumptions_OtherPayoffAge-Assumptions_CurrentAge-(A13-Assumptions_CurrentAge))/((1+Assumptions_OtherDebtRate)^MAX(1,Assumptions_OtherPayoffAge-Assumptions_CurrentAge-(A13-Assumptions_CurrentAge))-1)), 0) | P13: =M13+N13+O13 | Q13: =IF(L13<=0, 0, MAX(0, SUMPRODUCT(MAX(MIN(L13,FedBracketMax)-FedBracketMin,0)*FedBracketRate) - (FedBasicPersonal + IF(A13>=65, MAX(0, FedAgeAmount - MAX(0, L13-FedAgeThreshold)*FedAgeClawRate), 0) + IF(OR(H13>0, I13>0), FedPensionCredit, 0)) * FedCreditRate)) | R13: =L13-Q13 | S13: =MAX(0,P13-R13) | T13: =MIN(S13,AM12) | U13: =MAX(0,S13-T13) | V13: =MIN(U13,AN12) | W13: =MAX(0,U13-V13) | X13: =INDEX(FedBracketRate,MATCH(L13,FedBracketMin,1))+INDEX(ProvBracketRate,MATCH(L13,ProvBracketMin,1)) | Y13: =IF(W13>0, MIN(IF(X13>=1, W13, W13/(1-X13)), MAX(0,AL12-K13)), 0) | Z13: =K13+Y13 | AA13: =IF(W13>Y13*(1-X13), MIN(MAX(0,W13-Y13*(1-X13)),AO12), 0) | AB13: =MIN(Assumptions_OasMaxAnnual, MAX(0,(E13+F13+G13+H13+Z13-Assumptions_OasClawbackThresh)*Assumptions_OasClawbackRate)) | AC13: =MAX(0,G13-AB13) | AD13: =V13*IF(AN12>0, MAX(0,1-AS12/AN12), 0)*Assumptions_CapGainsRate | AE13: =E13+F13+AC13+H13+Z13+AD13 | AF13: =MAX(0, SUMPRODUCT(MAX(MIN(AE13,FedBracketMax)-FedBracketMin,0)*FedBracketRate) - (FedBasicPersonal + IF(A13>=65, MAX(0, FedAgeAmount - MAX(0, AE13-FedAgeThreshold)*FedAgeClawRate), 0) + IF(OR(H13>0, I13>0), FedPensionCredit, 0)) * FedCreditRate) | AG13: =MAX(0, SUMPRODUCT(MAX(MIN(AE13,ProvBracketMax)-ProvBracketMin,0)*ProvBracketRate) - (ProvBasicPersonal + IF(A13>=65, MAX(0, ProvAgeAmount - MAX(0, AE13-ProvAgeThreshold)*ProvAgeClawRate), 0) + IF(OR(H13>0, I13>0), ProvPensionCredit, 0)) * ProvCreditRate) + MAX(0, (MAX(0, SUMPRODUCT(MAX(MIN(AE13,ProvBracketMax)-ProvBracketMin,0)*ProvBracketRate) - (ProvBasicPersonal + IF(A13>=65, MAX(0, ProvAgeAmount - MAX(0, AE13-ProvAgeThreshold)*ProvAgeClawRate), 0) + IF(OR(H13>0, I13>0), ProvPensionCredit, 0)) * ProvCreditRate)-SurtaxThreshold1)*SurtaxRate1) + MAX(0, (MAX(0, SUMPRODUCT(MAX(MIN(AE13,ProvBracketMax)-ProvBracketMin,0)*ProvBracketRate) - (ProvBasicPersonal + IF(A13>=65, MAX(0, ProvAgeAmount - MAX(0, AE13-ProvAgeThreshold)*ProvAgeClawRate), 0) + IF(OR(H13>0, I13>0), ProvPensionCredit, 0)) * ProvCreditRate)-SurtaxThreshold2)*SurtaxRate2) | AH13: =AF13+AG13 | AI13: =E13+F13+AC13+H13+Z13+T13+V13+AA13-AH13 | AJ13: =AI13-M13-N13-O13 | AK13: =IF(AJ13>0, MIN(AJ13, Assumptions_TfsaAnnualLimit), 0) | AL13: =MAX(0,AL12-Z13)*(1+Assumptions_RealReturn) | AM13: =MAX(0,AM12-T13+AK13)*(1+Assumptions_TfsaReturn) | AN13: =MAX(0,AN12-V13+MAX(0,AJ13-AK13))*(1+Assumptions_NonRegReturn) | AO13: =MAX(0,AO12-AA13)*(1+Assumptions_RealReturn) | AP13: =IF(N13>0, MAX(0, AP12*(1+Assumptions_MortgageRate)-N13), 0) | AQ13: =AL13+AM13+AN13+AO13 | AR13: =AQ13+Assumptions_RealEstateValue-AP13 | AS13: =MAX(0,AS12*MAX(0,AN12-V13)/IF(AN12>0,AN12,1))+MAX(0,AJ13-AK13)
A14: =A13+1 | B14: =2026+(A14-Assumptions_CurrentAge) | C14: =IF(A14>=Assumptions_RetirementAge,1,0) | D14: =(1+Assumptions_Inflation)^(A14-Assumptions_CurrentAge) | E14: =IF(AND(C14=0,Assumptions_StillWorking=1),Assumptions_EmploymentIncome*D14,0) | F14: =IF(A14>=Assumptions_CppStartAge, Assumptions_CppMonthly*12*IF((Assumptions_CppStartAge-65)*12<0, 1+(Assumptions_CppStartAge-65)*12*CppEarlyReduction, 1+(Assumptions_CppStartAge-65)*12*CppLateIncrease)*D14, 0) | G14: =IF(A14>=Assumptions_OasStartAge, Assumptions_OasMonthly*12*(1+MAX(0, MIN(Assumptions_OasStartAge, OasMaxDeferAge)-OasStdStartAge)*12*OasDeferralBonus)*D14, 0) | H14: =IF(AND(Assumptions_PensionType="db",A14>=Assumptions_DbPensionStartAge), IF(Assumptions_DbPensionIndexed=1, Assumptions_DbPensionAnnual*D14, Assumptions_DbPensionAnnual), 0) | I14: =IF(AND(A14>=72,AL13>0), VLOOKUP(MIN(A14,95),RrifRates,2,TRUE)*AL13, 0) | J14: =IF(AND(Assumptions_MeltdownEnabled=1,A14>=Assumptions_MeltdownStartAge,A14<Assumptions_MeltdownTargetAge), MIN(Assumptions_MeltdownAnnual,AL13), 0) | K14: =MIN(MAX(I14,J14),AL13) | L14: =E14+F14+G14+H14+K14 | M14: =IF(C14=1, Assumptions_MonthlyExpenses*12*(1-Assumptions_ExpenseReduction), Assumptions_MonthlyExpenses*12)*D14 | N14: =IF(AND(AP13>0, (A14-Assumptions_CurrentAge)<Assumptions_MortgageYears), IF(Assumptions_MortgageRate=0, AP13/MAX(1,Assumptions_MortgageYears-(A14-Assumptions_CurrentAge)), AP13*Assumptions_MortgageRate*(1+Assumptions_MortgageRate)^MAX(1,Assumptions_MortgageYears-(A14-Assumptions_CurrentAge))/((1+Assumptions_MortgageRate)^MAX(1,Assumptions_MortgageYears-(A14-Assumptions_CurrentAge))-1)), 0) | O14: =IF(AND(Assumptions_ConsumerDebt>0, A14<Assumptions_ConsumerPayoffAge), IF(Assumptions_ConsumerDebtRate=0, Assumptions_ConsumerDebt/MAX(1,Assumptions_ConsumerPayoffAge-Assumptions_CurrentAge-(A14-Assumptions_CurrentAge)), Assumptions_ConsumerDebt*Assumptions_ConsumerDebtRate*(1+Assumptions_ConsumerDebtRate)^MAX(1,Assumptions_ConsumerPayoffAge-Assumptions_CurrentAge-(A14-Assumptions_CurrentAge))/((1+Assumptions_ConsumerDebtRate)^MAX(1,Assumptions_ConsumerPayoffAge-Assumptions_CurrentAge-(A14-Assumptions_CurrentAge))-1)), 0)+IF(AND(Assumptions_OtherDebt>0, A14<Assumptions_OtherPayoffAge), IF(Assumptions_OtherDebtRate=0, Assumptions_OtherDebt/MAX(1,Assumptions_OtherPayoffAge-Assumptions_CurrentAge-(A14-Assumptions_CurrentAge)), Assumptions_OtherDebt*Assumptions_OtherDebtRate*(1+Assumptions_OtherDebtRate)^MAX(1,Assumptions_OtherPayoffAge-Assumptions_CurrentAge-(A14-Assumptions_CurrentAge))/((1+Assumptions_OtherDebtRate)^MAX(1,Assumptions_OtherPayoffAge-Assumptions_CurrentAge-(A14-Assumptions_CurrentAge))-1)), 0) | P14: =M14+N14+O14 | Q14: =IF(L14<=0, 0, MAX(0, SUMPRODUCT(MAX(MIN(L14,FedBracketMax)-FedBracketMin,0)*FedBracketRate) - (FedBasicPersonal + IF(A14>=65, MAX(0, FedAgeAmount - MAX(0, L14-FedAgeThreshold)*FedAgeClawRate), 0) + IF(OR(H14>0, I14>0), FedPensionCredit, 0)) * FedCreditRate)) | R14: =L14-Q14 | S14: =MAX(0,P14-R14) | T14: =MIN(S14,AM13) | U14: =MAX(0,S14-T14) | V14: =MIN(U14,AN13) | W14: =MAX(0,U14-V14) | X14: =INDEX(FedBracketRate,MATCH(L14,FedBracketMin,1))+INDEX(ProvBracketRate,MATCH(L14,ProvBracketMin,1)) | Y14: =IF(W14>0, MIN(IF(X14>=1, W14, W14/(1-X14)), MAX(0,AL13-K14)), 0) | Z14: =K14+Y14 | AA14: =IF(W14>Y14*(1-X14), MIN(MAX(0,W14-Y14*(1-X14)),AO13), 0) | AB14: =MIN(Assumptions_OasMaxAnnual, MAX(0,(E14+F14+G14+H14+Z14-Assumptions_OasClawbackThresh)*Assumptions_OasClawbackRate)) | AC14: =MAX(0,G14-AB14) | AD14: =V14*IF(AN13>0, MAX(0,1-AS13/AN13), 0)*Assumptions_CapGainsRate | AE14: =E14+F14+AC14+H14+Z14+AD14 | AF14: =MAX(0, SUMPRODUCT(MAX(MIN(AE14,FedBracketMax)-FedBracketMin,0)*FedBracketRate) - (FedBasicPersonal + IF(A14>=65, MAX(0, FedAgeAmount - MAX(0, AE14-FedAgeThreshold)*FedAgeClawRate), 0) + IF(OR(H14>0, I14>0), FedPensionCredit, 0)) * FedCreditRate) | AG14: =MAX(0, SUMPRODUCT(MAX(MIN(AE14,ProvBracketMax)-ProvBracketMin,0)*ProvBracketRate) - (ProvBasicPersonal + IF(A14>=65, MAX(0, ProvAgeAmount - MAX(0, AE14-ProvAgeThreshold)*ProvAgeClawRate), 0) + IF(OR(H14>0, I14>0), ProvPensionCredit, 0)) * ProvCreditRate) + MAX(0, (MAX(0, SUMPRODUCT(MAX(MIN(AE14,ProvBracketMax)-ProvBracketMin,0)*ProvBracketRate) - (ProvBasicPersonal + IF(A14>=65, MAX(0, ProvAgeAmount - MAX(0, AE14-ProvAgeThreshold)*ProvAgeClawRate), 0) + IF(OR(H14>0, I14>0), ProvPensionCredit, 0)) * ProvCreditRate)-SurtaxThreshold1)*SurtaxRate1) + MAX(0, (MAX(0, SUMPRODUCT(MAX(MIN(AE14,ProvBracketMax)-ProvBracketMin,0)*ProvBracketRate) - (ProvBasicPersonal + IF(A14>=65, MAX(0, ProvAgeAmount - MAX(0, AE14-ProvAgeThreshold)*ProvAgeClawRate), 0) + IF(OR(H14>0, I14>0), ProvPensionCredit, 0)) * ProvCreditRate)-SurtaxThreshold2)*SurtaxRate2) | AH14: =AF14+AG14 | AI14: =E14+F14+AC14+H14+Z14+T14+V14+AA14-AH14 | AJ14: =AI14-M14-N14-O14 | AK14: =IF(AJ14>0, MIN(AJ14, Assumptions_TfsaAnnualLimit), 0) | AL14: =MAX(0,AL13-Z14)*(1+Assumptions_RealReturn) | AM14: =MAX(0,AM13-T14+AK14)*(1+Assumptions_TfsaReturn) | AN14: =MAX(0,AN13-V14+MAX(0,AJ14-AK14))*(1+Assumptions_NonRegReturn) | AO14: =MAX(0,AO13-AA14)*(1+Assumptions_RealReturn) | AP14: =IF(N14>0, MAX(0, AP13*(1+Assumptions_MortgageRate)-N14), 0) | AQ14: =AL14+AM14+AN14+AO14 | AR14: =AQ14+Assumptions_RealEstateValue-AP14 | AS14: =MAX(0,AS13*MAX(0,AN13-V14)/IF(AN13>0,AN13,1))+MAX(0,AJ14-AK14)
A15: =A14+1 | B15: =2026+(A15-Assumptions_CurrentAge) | C15: =IF(A15>=Assumptions_RetirementAge,1,0) | D15: =(1+Assumptions_Inflation)^(A15-Assumptions_CurrentAge) | E15: =IF(AND(C15=0,Assumptions_StillWorking=1),Assumptions_EmploymentIncome*D15,0) | F15: =IF(A15>=Assumptions_CppStartAge, Assumptions_CppMonthly*12*IF((Assumptions_CppStartAge-65)*12<0, 1+(Assumptions_CppStartAge-65)*12*CppEarlyReduction, 1+(Assumptions_CppStartAge-65)*12*CppLateIncrease)*D15, 0) | G15: =IF(A15>=Assumptions_OasStartAge, Assumptions_OasMonthly*12*(1+MAX(0, MIN(Assumptions_OasStartAge, OasMaxDeferAge)-OasStdStartAge)*12*OasDeferralBonus)*D15, 0) | H15: =IF(AND(Assumptions_PensionType="db",A15>=Assumptions_DbPensionStartAge), IF(Assumptions_DbPensionIndexed=1, Assumptions_DbPensionAnnual*D15, Assumptions_DbPensionAnnual), 0) | I15: =IF(AND(A15>=72,AL14>0), VLOOKUP(MIN(A15,95),RrifRates,2,TRUE)*AL14, 0) | J15: =IF(AND(Assumptions_MeltdownEnabled=1,A15>=Assumptions_MeltdownStartAge,A15<Assumptions_MeltdownTargetAge), MIN(Assumptions_MeltdownAnnual,AL14), 0) | K15: =MIN(MAX(I15,J15),AL14) | L15: =E15+F15+G15+H15+K15 | M15: =IF(C15=1, Assumptions_MonthlyExpenses*12*(1-Assumptions_ExpenseReduction), Assumptions_MonthlyExpenses*12)*D15 | N15: =IF(AND(AP14>0, (A15-Assumptions_CurrentAge)<Assumptions_MortgageYears), IF(Assumptions_MortgageRate=0, AP14/MAX(1,Assumptions_MortgageYears-(A15-Assumptions_CurrentAge)), AP14*Assumptions_MortgageRate*(1+Assumptions_MortgageRate)^MAX(1,Assumptions_MortgageYears-(A15-Assumptions_CurrentAge))/((1+Assumptions_MortgageRate)^MAX(1,Assumptions_MortgageYears-(A15-Assumptions_CurrentAge))-1)), 0) | O15: =IF(AND(Assumptions_ConsumerDebt>0, A15<Assumptions_ConsumerPayoffAge), IF(Assumptions_ConsumerDebtRate=0, Assumptions_ConsumerDebt/MAX(1,Assumptions_ConsumerPayoffAge-Assumptions_CurrentAge-(A15-Assumptions_CurrentAge)), Assumptions_ConsumerDebt*Assumptions_ConsumerDebtRate*(1+Assumptions_ConsumerDebtRate)^MAX(1,Assumptions_ConsumerPayoffAge-Assumptions_CurrentAge-(A15-Assumptions_CurrentAge))/((1+Assumptions_ConsumerDebtRate)^MAX(1,Assumptions_ConsumerPayoffAge-Assumptions_CurrentAge-(A15-Assumptions_CurrentAge))-1)), 0)+IF(AND(Assumptions_OtherDebt>0, A15<Assumptions_OtherPayoffAge), IF(Assumptions_OtherDebtRate=0, Assumptions_OtherDebt/MAX(1,Assumptions_OtherPayoffAge-Assumptions_CurrentAge-(A15-Assumptions_CurrentAge)), Assumptions_OtherDebt*Assumptions_OtherDebtRate*(1+Assumptions_OtherDebtRate)^MAX(1,Assumptions_OtherPayoffAge-Assumptions_CurrentAge-(A15-Assumptions_CurrentAge))/((1+Assumptions_OtherDebtRate)^MAX(1,Assumptions_OtherPayoffAge-Assumptions_CurrentAge-(A15-Assumptions_CurrentAge))-1)), 0) | P15: =M15+N15+O15 | Q15: =IF(L15<=0, 0, MAX(0, SUMPRODUCT(MAX(MIN(L15,FedBracketMax)-FedBracketMin,0)*FedBracketRate) - (FedBasicPersonal + IF(A15>=65, MAX(0, FedAgeAmount - MAX(0, L15-FedAgeThreshold)*FedAgeClawRate), 0) + IF(OR(H15>0, I15>0), FedPensionCredit, 0)) * FedCreditRate)) | R15: =L15-Q15 | S15: =MAX(0,P15-R15) | T15: =MIN(S15,AM14) | U15: =MAX(0,S15-T15) | V15: =MIN(U15,AN14) | W15: =MAX(0,U15-V15) | X15: =INDEX(FedBracketRate,MATCH(L15,FedBracketMin,1))+INDEX(ProvBracketRate,MATCH(L15,ProvBracketMin,1)) | Y15: =IF(W15>0, MIN(IF(X15>=1, W15, W15/(1-X15)), MAX(0,AL14-K15)), 0) | Z15: =K15+Y15 | AA15: =IF(W15>Y15*(1-X15), MIN(MAX(0,W15-Y15*(1-X15)),AO14), 0) | AB15: =MIN(Assumptions_OasMaxAnnual, MAX(0,(E15+F15+G15+H15+Z15-Assumptions_OasClawbackThresh)*Assumptions_OasClawbackRate)) | AC15: =MAX(0,G15-AB15) | AD15: =V15*IF(AN14>0, MAX(0,1-AS14/AN14), 0)*Assumptions_CapGainsRate | AE15: =E15+F15+AC15+H15+Z15+AD15 | AF15: =MAX(0, SUMPRODUCT(MAX(MIN(AE15,FedBracketMax)-FedBracketMin,0)*FedBracketRate) - (FedBasicPersonal + IF(A15>=65, MAX(0, FedAgeAmount - MAX(0, AE15-FedAgeThreshold)*FedAgeClawRate), 0) + IF(OR(H15>0, I15>0), FedPensionCredit, 0)) * FedCreditRate) | AG15: =MAX(0, SUMPRODUCT(MAX(MIN(AE15,ProvBracketMax)-ProvBracketMin,0)*ProvBracketRate) - (ProvBasicPersonal + IF(A15>=65, MAX(0, ProvAgeAmount - MAX(0, AE15-ProvAgeThreshold)*ProvAgeClawRate), 0) + IF(OR(H15>0, I15>0), ProvPensionCredit, 0)) * ProvCreditRate) + MAX(0, (MAX(0, SUMPRODUCT(MAX(MIN(AE15,ProvBracketMax)-ProvBracketMin,0)*ProvBracketRate) - (ProvBasicPersonal + IF(A15>=65, MAX(0, ProvAgeAmount - MAX(0, AE15-ProvAgeThreshold)*ProvAgeClawRate), 0) + IF(OR(H15>0, I15>0), ProvPensionCredit, 0)) * ProvCreditRate)-SurtaxThreshold1)*SurtaxRate1) + MAX(0, (MAX(0, SUMPRODUCT(MAX(MIN(AE15,ProvBracketMax)-ProvBracketMin,0)*ProvBracketRate) - (ProvBasicPersonal + IF(A15>=65, MAX(0, ProvAgeAmount - MAX(0, AE15-ProvAgeThreshold)*ProvAgeClawRate), 0) + IF(OR(H15>0, I15>0), ProvPensionCredit, 0)) * ProvCreditRate)-SurtaxThreshold2)*SurtaxRate2) | AH15: =AF15+AG15 | AI15: =E15+F15+AC15+H15+Z15+T15+V15+AA15-AH15 | AJ15: =AI15-M15-N15-O15 | AK15: =IF(AJ15>0, MIN(AJ15, Assumptions_TfsaAnnualLimit), 0) | AL15: =MAX(0,AL14-Z15)*(1+Assumptions_RealReturn) | AM15: =MAX(0,AM14-T15+AK15)*(1+Assumptions_TfsaReturn) | AN15: =MAX(0,AN14-V15+MAX(0,AJ15-AK15))*(1+Assumptions_NonRegReturn) | AO15: =MAX(0,AO14-AA15)*(1+Assumptions_RealReturn) | AP15: =IF(N15>0, MAX(0, AP14*(1+Assumptions_MortgageRate)-N15), 0) | AQ15: =AL15+AM15+AN15+AO15 | AR15: =AQ15+Assumptions_RealEstateValue-AP15 | AS15: =MAX(0,AS14*MAX(0,AN14-V15)/IF(AN14>0,AN14,1))+MAX(0,AJ15-AK15)
A16: =A15+1 | B16: =2026+(A16-Assumptions_CurrentAge) | C16: =IF(A16>=Assumptions_RetirementAge,1,0) | D16: =(1+Assumptions_Inflation)^(A16-Assumptions_CurrentAge) | E16: =IF(AND(C16=0,Assumptions_StillWorking=1),Assumptions_EmploymentIncome*D16,0) | F16: =IF(A16>=Assumptions_CppStartAge, Assumptions_CppMonthly*12*IF((Assumptions_CppStartAge-65)*12<0, 1+(Assumptions_CppStartAge-65)*12*CppEarlyReduction, 1+(Assumptions_CppStartAge-65)*12*CppLateIncrease)*D16, 0) | G16: =IF(A16>=Assumptions_OasStartAge, Assumptions_OasMonthly*12*(1+MAX(0, MIN(Assumptions_OasStartAge, OasMaxDeferAge)-OasStdStartAge)*12*OasDeferralBonus)*D16, 0) | H16: =IF(AND(Assumptions_PensionType="db",A16>=Assumptions_DbPensionStartAge), IF(Assumptions_DbPensionIndexed=1, Assumptions_DbPensionAnnual*D16, Assumptions_DbPensionAnnual), 0) | I16: =IF(AND(A16>=72,AL15>0), VLOOKUP(MIN(A16,95),RrifRates,2,TRUE)*AL15, 0) | J16: =IF(AND(Assumptions_MeltdownEnabled=1,A16>=Assumptions_MeltdownStartAge,A16<Assumptions_MeltdownTargetAge), MIN(Assumptions_MeltdownAnnual,AL15), 0) | K16: =MIN(MAX(I16,J16),AL15) | L16: =E16+F16+G16+H16+K16 | M16: =IF(C16=1, Assumptions_MonthlyExpenses*12*(1-Assumptions_ExpenseReduction), Assumptions_MonthlyExpenses*12)*D16 | N16: =IF(AND(AP15>0, (A16-Assumptions_CurrentAge)<Assumptions_MortgageYears), IF(Assumptions_MortgageRate=0, AP15/MAX(1,Assumptions_MortgageYears-(A16-Assumptions_CurrentAge)), AP15*Assumptions_MortgageRate*(1+Assumptions_MortgageRate)^MAX(1,Assumptions_MortgageYears-(A16-Assumptions_CurrentAge))/((1+Assumptions_MortgageRate)^MAX(1,Assumptions_MortgageYears-(A16-Assumptions_CurrentAge))-1)), 0) | O16: =IF(AND(Assumptions_ConsumerDebt>0, A16<Assumptions_ConsumerPayoffAge), IF(Assumptions_ConsumerDebtRate=0, Assumptions_ConsumerDebt/MAX(1,Assumptions_ConsumerPayoffAge-Assumptions_CurrentAge-(A16-Assumptions_CurrentAge)), Assumptions_ConsumerDebt*Assumptions_ConsumerDebtRate*(1+Assumptions_ConsumerDebtRate)^MAX(1,Assumptions_ConsumerPayoffAge-Assumptions_CurrentAge-(A16-Assumptions_CurrentAge))/((1+Assumptions_ConsumerDebtRate)^MAX(1,Assumptions_ConsumerPayoffAge-Assumptions_CurrentAge-(A16-Assumptions_CurrentAge))-1)), 0)+IF(AND(Assumptions_OtherDebt>0, A16<Assumptions_OtherPayoffAge), IF(Assumptions_OtherDebtRate=0, Assumptions_OtherDebt/MAX(1,Assumptions_OtherPayoffAge-Assumptions_CurrentAge-(A16-Assumptions_CurrentAge)), Assumptions_OtherDebt*Assumptions_OtherDebtRate*(1+Assumptions_OtherDebtRate)^MAX(1,Assumptions_OtherPayoffAge-Assumptions_CurrentAge-(A16-Assumptions_CurrentAge))/((1+Assumptions_OtherDebtRate)^MAX(1,Assumptions_OtherPayoffAge-Assumptions_CurrentAge-(A16-Assumptions_CurrentAge))-1)), 0) | P16: =M16+N16+O16 | Q16: =IF(L16<=0, 0, MAX(0, SUMPRODUCT(MAX(MIN(L16,FedBracketMax)-FedBracketMin,0)*FedBracketRate) - (FedBasicPersonal + IF(A16>=65, MAX(0, FedAgeAmount - MAX(0, L16-FedAgeThreshold)*FedAgeClawRate), 0) + IF(OR(H16>0, I16>0), FedPensionCredit, 0)) * FedCreditRate)) | R16: =L16-Q16 | S16: =MAX(0,P16-R16) | T16: =MIN(S16,AM15) | U16: =MAX(0,S16-T16) | V16: =MIN(U16,AN15) | W16: =MAX(0,U16-V16) | X16: =INDEX(FedBracketRate,MATCH(L16,FedBracketMin,1))+INDEX(ProvBracketRate,MATCH(L16,ProvBracketMin,1)) | Y16: =IF(W16>0, MIN(IF(X16>=1, W16, W16/(1-X16)), MAX(0,AL15-K16)), 0) | Z16: =K16+Y16 | AA16: =IF(W16>Y16*(1-X16), MIN(MAX(0,W16-Y16*(1-X16)),AO15), 0) | AB16: =MIN(Assumptions_OasMaxAnnual, MAX(0,(E16+F16+G16+H16+Z16-Assumptions_OasClawbackThresh)*Assumptions_OasClawbackRate)) | AC16: =MAX(0,G16-AB16) | AD16: =V16*IF(AN15>0, MAX(0,1-AS15/AN15), 0)*Assumptions_CapGainsRate | AE16: =E16+F16+AC16+H16+Z16+AD16 | AF16: =MAX(0, SUMPRODUCT(MAX(MIN(AE16,FedBracketMax)-FedBracketMin,0)*FedBracketRate) - (FedBasicPersonal + IF(A16>=65, MAX(0, FedAgeAmount - MAX(0, AE16-FedAgeThreshold)*FedAgeClawRate), 0) + IF(OR(H16>0, I16>0), FedPensionCredit, 0)) * FedCreditRate) | AG16: =MAX(0, SUMPRODUCT(MAX(MIN(AE16,ProvBracketMax)-ProvBracketMin,0)*ProvBracketRate) - (ProvBasicPersonal + IF(A16>=65, MAX(0, ProvAgeAmount - MAX(0, AE16-ProvAgeThreshold)*ProvAgeClawRate), 0) + IF(OR(H16>0, I16>0), ProvPensionCredit, 0)) * ProvCreditRate) + MAX(0, (MAX(0, SUMPRODUCT(MAX(MIN(AE16,ProvBracketMax)-ProvBracketMin,0)*ProvBracketRate) - (ProvBasicPersonal + IF(A16>=65, MAX(0, ProvAgeAmount - MAX(0, AE16-ProvAgeThreshold)*ProvAgeClawRate), 0) + IF(OR(H16>0, I16>0), ProvPensionCredit, 0)) * ProvCreditRate)-SurtaxThreshold1)*SurtaxRate1) + MAX(0, (MAX(0, SUMPRODUCT(MAX(MIN(AE16,ProvBracketMax)-ProvBracketMin,0)*ProvBracketRate) - (ProvBasicPersonal + IF(A16>=65, MAX(0, ProvAgeAmount - MAX(0, AE16-ProvAgeThreshold)*ProvAgeClawRate), 0) + IF(OR(H16>0, I16>0), ProvPensionCredit, 0)) * ProvCreditRate)-SurtaxThreshold2)*SurtaxRate2) | AH16: =AF16+AG16 | AI16: =E16+F16+AC16+H16+Z16+T16+V16+AA16-AH16 | AJ16: =AI16-M16-N16-O16 | AK16: =IF(AJ16>0, MIN(AJ16, Assumptions_TfsaAnnualLimit), 0) | AL16: =MAX(0,AL15-Z16)*(1+Assumptions_RealReturn) | AM16: =MAX(0,AM15-T16+AK16)*(1+Assumptions_TfsaReturn) | AN16: =MAX(0,AN15-V16+MAX(0,AJ16-AK16))*(1+Assumptions_NonRegReturn) | AO16: =MAX(0,AO15-AA16)*(1+Assumptions_RealReturn) | AP16: =IF(N16>0, MAX(0, AP15*(1+Assumptions_MortgageRate)-N16), 0) | AQ16: =AL16+AM16+AN16+AO16 | AR16: =AQ16+Assumptions_RealEstateValue-AP16 | AS16: =MAX(0,AS15*MAX(0,AN15-V16)/IF(AN15>0,AN15,1))+MAX(0,AJ16-AK16)
A17: =A16+1 | B17: =2026+(A17-Assumptions_CurrentAge) | C17: =IF(A17>=Assumptions_RetirementAge,1,0) | D17: =(1+Assumptions_Inflation)^(A17-Assumptions_CurrentAge) | E17: =IF(AND(C17=0,Assumptions_StillWorking=1),Assumptions_EmploymentIncome*D17,0) | F17: =IF(A17>=Assumptions_CppStartAge, Assumptions_CppMonthly*12*IF((Assumptions_CppStartAge-65)*12<0, 1+(Assumptions_CppStartAge-65)*12*CppEarlyReduction, 1+(Assumptions_CppStartAge-65)*12*CppLateIncrease)*D17, 0) | G17: =IF(A17>=Assumptions_OasStartAge, Assumptions_OasMonthly*12*(1+MAX(0, MIN(Assumptions_OasStartAge, OasMaxDeferAge)-OasStdStartAge)*12*OasDeferralBonus)*D17, 0) | H17: =IF(AND(Assumptions_PensionType="db",A17>=Assumptions_DbPensionStartAge), IF(Assumptions_DbPensionIndexed=1, Assumptions_DbPensionAnnual*D17, Assumptions_DbPensionAnnual), 0) | I17: =IF(AND(A17>=72,AL16>0), VLOOKUP(MIN(A17,95),RrifRates,2,TRUE)*AL16, 0) | J17: =IF(AND(Assumptions_MeltdownEnabled=1,A17>=Assumptions_MeltdownStartAge,A17<Assumptions_MeltdownTargetAge), MIN(Assumptions_MeltdownAnnual,AL16), 0) | K17: =MIN(MAX(I17,J17),AL16) | L17: =E17+F17+G17+H17+K17 | M17: =IF(C17=1, Assumptions_MonthlyExpenses*12*(1-Assumptions_ExpenseReduction), Assumptions_MonthlyExpenses*12)*D17 | N17: =IF(AND(AP16>0, (A17-Assumptions_CurrentAge)<Assumptions_MortgageYears), IF(Assumptions_MortgageRate=0, AP16/MAX(1,Assumptions_MortgageYears-(A17-Assumptions_CurrentAge)), AP16*Assumptions_MortgageRate*(1+Assumptions_MortgageRate)^MAX(1,Assumptions_MortgageYears-(A17-Assumptions_CurrentAge))/((1+Assumptions_MortgageRate)^MAX(1,Assumptions_MortgageYears-(A17-Assumptions_CurrentAge))-1)), 0) | O17: =IF(AND(Assumptions_ConsumerDebt>0, A17<Assumptions_ConsumerPayoffAge), IF(Assumptions_ConsumerDebtRate=0, Assumptions_ConsumerDebt/MAX(1,Assumptions_ConsumerPayoffAge-Assumptions_CurrentAge-(A17-Assumptions_CurrentAge)), Assumptions_ConsumerDebt*Assumptions_ConsumerDebtRate*(1+Assumptions_ConsumerDebtRate)^MAX(1,Assumptions_ConsumerPayoffAge-Assumptions_CurrentAge-(A17-Assumptions_CurrentAge))/((1+Assumptions_ConsumerDebtRate)^MAX(1,Assumptions_ConsumerPayoffAge-Assumptions_CurrentAge-(A17-Assumptions_CurrentAge))-1)), 0)+IF(AND(Assumptions_OtherDebt>0, A17<Assumptions_OtherPayoffAge), IF(Assumptions_OtherDebtRate=0, Assumptions_OtherDebt/MAX(1,Assumptions_OtherPayoffAge-Assumptions_CurrentAge-(A17-Assumptions_CurrentAge)), Assumptions_OtherDebt*Assumptions_OtherDebtRate*(1+Assumptions_OtherDebtRate)^MAX(1,Assumptions_OtherPayoffAge-Assumptions_CurrentAge-(A17-Assumptions_CurrentAge))/((1+Assumptions_OtherDebtRate)^MAX(1,Assumptions_OtherPayoffAge-Assumptions_CurrentAge-(A17-Assumptions_CurrentAge))-1)), 0) | P17: =M17+N17+O17 | Q17: =IF(L17<=0, 0, MAX(0, SUMPRODUCT(MAX(MIN(L17,FedBracketMax)-FedBracketMin,0)*FedBracketRate) - (FedBasicPersonal + IF(A17>=65, MAX(0, FedAgeAmount - MAX(0, L17-FedAgeThreshold)*FedAgeClawRate), 0) + IF(OR(H17>0, I17>0), FedPensionCredit, 0)) * FedCreditRate)) | R17: =L17-Q17 | S17: =MAX(0,P17-R17) | T17: =MIN(S17,AM16) | U17: =MAX(0,S17-T17) | V17: =MIN(U17,AN16) | W17: =MAX(0,U17-V17) | X17: =INDEX(FedBracketRate,MATCH(L17,FedBracketMin,1))+INDEX(ProvBracketRate,MATCH(L17,ProvBracketMin,1)) | Y17: =IF(W17>0, MIN(IF(X17>=1, W17, W17/(1-X17)), MAX(0,AL16-K17)), 0) | Z17: =K17+Y17 | AA17: =IF(W17>Y17*(1-X17), MIN(MAX(0,W17-Y17*(1-X17)),AO16), 0) | AB17: =MIN(Assumptions_OasMaxAnnual, MAX(0,(E17+F17+G17+H17+Z17-Assumptions_OasClawbackThresh)*Assumptions_OasClawbackRate)) | AC17: =MAX(0,G17-AB17) | AD17: =V17*IF(AN16>0, MAX(0,1-AS16/AN16), 0)*Assumptions_CapGainsRate | AE17: =E17+F17+AC17+H17+Z17+AD17 | AF17: =MAX(0, SUMPRODUCT(MAX(MIN(AE17,FedBracketMax)-FedBracketMin,0)*FedBracketRate) - (FedBasicPersonal + IF(A17>=65, MAX(0, FedAgeAmount - MAX(0, AE17-FedAgeThreshold)*FedAgeClawRate), 0) + IF(OR(H17>0, I17>0), FedPensionCredit, 0)) * FedCreditRate) | AG17: =MAX(0, SUMPRODUCT(MAX(MIN(AE17,ProvBracketMax)-ProvBracketMin,0)*ProvBracketRate) - (ProvBasicPersonal + IF(A17>=65, MAX(0, ProvAgeAmount - MAX(0, AE17-ProvAgeThreshold)*ProvAgeClawRate), 0) + IF(OR(H17>0, I17>0), ProvPensionCredit, 0)) * ProvCreditRate) + MAX(0, (MAX(0, SUMPRODUCT(MAX(MIN(AE17,ProvBracketMax)-ProvBracketMin,0)*ProvBracketRate) - (ProvBasicPersonal + IF(A17>=65, MAX(0, ProvAgeAmount - MAX(0, AE17-ProvAgeThreshold)*ProvAgeClawRate), 0) + IF(OR(H17>0, I17>0), ProvPensionCredit, 0)) * ProvCreditRate)-SurtaxThreshold1)*SurtaxRate1) + MAX(0, (MAX(0, SUMPRODUCT(MAX(MIN(AE17,ProvBracketMax)-ProvBracketMin,0)*ProvBracketRate) - (ProvBasicPersonal + IF(A17>=65, MAX(0, ProvAgeAmount - MAX(0, AE17-ProvAgeThreshold)*ProvAgeClawRate), 0) + IF(OR(H17>0, I17>0), ProvPensionCredit, 0)) * ProvCreditRate)-SurtaxThreshold2)*SurtaxRate2) | AH17: =AF17+AG17 | AI17: =E17+F17+AC17+H17+Z17+T17+V17+AA17-AH17 | AJ17: =AI17-M17-N17-O17 | AK17: =IF(AJ17>0, MIN(AJ17, Assumptions_TfsaAnnualLimit), 0) | AL17: =MAX(0,AL16-Z17)*(1+Assumptions_RealReturn) | AM17: =MAX(0,AM16-T17+AK17)*(1+Assumptions_TfsaReturn) | AN17: =MAX(0,AN16-V17+MAX(0,AJ17-AK17))*(1+Assumptions_NonRegReturn) | AO17: =MAX(0,AO16-AA17)*(1+Assumptions_RealReturn) | AP17: =IF(N17>0, MAX(0, AP16*(1+Assumptions_MortgageRate)-N17), 0) | AQ17: =AL17+AM17+AN17+AO17 | AR17: =AQ17+Assumptions_RealEstateValue-AP17 | AS17: =MAX(0,AS16*MAX(0,AN16-V17)/IF(AN16>0,AN16,1))+MAX(0,AJ17-AK17)
A18: =A17+1 | B18: =2026+(A18-Assumptions_CurrentAge) | C18: =IF(A18>=Assumptions_RetirementAge,1,0) | D18: =(1+Assumptions_Inflation)^(A18-Assumptions_CurrentAge) | E18: =IF(AND(C18=0,Assumptions_StillWorking=1),Assumptions_EmploymentIncome*D18,0) | F18: =IF(A18>=Assumptions_CppStartAge, Assumptions_CppMonthly*12*IF((Assumptions_CppStartAge-65)*12<0, 1+(Assumptions_CppStartAge-65)*12*CppEarlyReduction, 1+(Assumptions_CppStartAge-65)*12*CppLateIncrease)*D18, 0) | G18: =IF(A18>=Assumptions_OasStartAge, Assumptions_OasMonthly*12*(1+MAX(0, MIN(Assumptions_OasStartAge, OasMaxDeferAge)-OasStdStartAge)*12*OasDeferralBonus)*D18, 0) | H18: =IF(AND(Assumptions_PensionType="db",A18>=Assumptions_DbPensionStartAge), IF(Assumptions_DbPensionIndexed=1, Assumptions_DbPensionAnnual*D18, Assumptions_DbPensionAnnual), 0) | I18: =IF(AND(A18>=72,AL17>0), VLOOKUP(MIN(A18,95),RrifRates,2,TRUE)*AL17, 0) | J18: =IF(AND(Assumptions_MeltdownEnabled=1,A18>=Assumptions_MeltdownStartAge,A18<Assumptions_MeltdownTargetAge), MIN(Assumptions_MeltdownAnnual,AL17), 0) | K18: =MIN(MAX(I18,J18),AL17) | L18: =E18+F18+G18+H18+K18 | M18: =IF(C18=1, Assumptions_MonthlyExpenses*12*(1-Assumptions_ExpenseReduction), Assumptions_MonthlyExpenses*12)*D18 | N18: =IF(AND(AP17>0, (A18-Assumptions_CurrentAge)<Assumptions_MortgageYears), IF(Assumptions_MortgageRate=0, AP17/MAX(1,Assumptions_MortgageYears-(A18-Assumptions_CurrentAge)), AP17*Assumptions_MortgageRate*(1+Assumptions_MortgageRate)^MAX(1,Assumptions_MortgageYears-(A18-Assumptions_CurrentAge))/((1+Assumptions_MortgageRate)^MAX(1,Assumptions_MortgageYears-(A18-Assumptions_CurrentAge))-1)), 0) | O18: =IF(AND(Assumptions_ConsumerDebt>0, A18<Assumptions_ConsumerPayoffAge), IF(Assumptions_ConsumerDebtRate=0, Assumptions_ConsumerDebt/MAX(1,Assumptions_ConsumerPayoffAge-Assumptions_CurrentAge-(A18-Assumptions_CurrentAge)), Assumptions_ConsumerDebt*Assumptions_ConsumerDebtRate*(1+Assumptions_ConsumerDebtRate)^MAX(1,Assumptions_ConsumerPayoffAge-Assumptions_CurrentAge-(A18-Assumptions_CurrentAge))/((1+Assumptions_ConsumerDebtRate)^MAX(1,Assumptions_ConsumerPayoffAge-Assumptions_CurrentAge-(A18-Assumptions_CurrentAge))-1)), 0)+IF(AND(Assumptions_OtherDebt>0, A18<Assumptions_OtherPayoffAge), IF(Assumptions_OtherDebtRate=0, Assumptions_OtherDebt/MAX(1,Assumptions_OtherPayoffAge-Assumptions_CurrentAge-(A18-Assumptions_CurrentAge)), Assumptions_OtherDebt*Assumptions_OtherDebtRate*(1+Assumptions_OtherDebtRate)^MAX(1,Assumptions_OtherPayoffAge-Assumptions_CurrentAge-(A18-Assumptions_CurrentAge))/((1+Assumptions_OtherDebtRate)^MAX(1,Assumptions_OtherPayoffAge-Assumptions_CurrentAge-(A18-Assumptions_CurrentAge))-1)), 0) | P18: =M18+N18+O18 | Q18: =IF(L18<=0, 0, MAX(0, SUMPRODUCT(MAX(MIN(L18,FedBracketMax)-FedBracketMin,0)*FedBracketRate) - (FedBasicPersonal + IF(A18>=65, MAX(0, FedAgeAmount - MAX(0, L18-FedAgeThreshold)*FedAgeClawRate), 0) + IF(OR(H18>0, I18>0), FedPensionCredit, 0)) * FedCreditRate)) | R18: =L18-Q18 | S18: =MAX(0,P18-R18) | T18: =MIN(S18,AM17) | U18: =MAX(0,S18-T18) | V18: =MIN(U18,AN17) | W18: =MAX(0,U18-V18) | X18: =INDEX(FedBracketRate,MATCH(L18,FedBracketMin,1))+INDEX(ProvBracketRate,MATCH(L18,ProvBracketMin,1)) | Y18: =IF(W18>0, MIN(IF(X18>=1, W18, W18/(1-X18)), MAX(0,AL17-K18)), 0) | Z18: =K18+Y18 | AA18: =IF(W18>Y18*(1-X18), MIN(MAX(0,W18-Y18*(1-X18)),AO17), 0) | AB18: =MIN(Assumptions_OasMaxAnnual, MAX(0,(E18+F18+G18+H18+Z18-Assumptions_OasClawbackThresh)*Assumptions_OasClawbackRate)) | AC18: =MAX(0,G18-AB18) | AD18: =V18*IF(AN17>0, MAX(0,1-AS17/AN17), 0)*Assumptions_CapGainsRate | AE18: =E18+F18+AC18+H18+Z18+AD18 | AF18: =MAX(0, SUMPRODUCT(MAX(MIN(AE18,FedBracketMax)-FedBracketMin,0)*FedBracketRate) - (FedBasicPersonal + IF(A18>=65, MAX(0, FedAgeAmount - MAX(0, AE18-FedAgeThreshold)*FedAgeClawRate), 0) + IF(OR(H18>0, I18>0), FedPensionCredit, 0)) * FedCreditRate) | AG18: =MAX(0, SUMPRODUCT(MAX(MIN(AE18,ProvBracketMax)-ProvBracketMin,0)*ProvBracketRate) - (ProvBasicPersonal + IF(A18>=65, MAX(0, ProvAgeAmount - MAX(0, AE18-ProvAgeThreshold)*ProvAgeClawRate), 0) + IF(OR(H18>0, I18>0), ProvPensionCredit, 0)) * ProvCreditRate) + MAX(0, (MAX(0, SUMPRODUCT(MAX(MIN(AE18,ProvBracketMax)-ProvBracketMin,0)*ProvBracketRate) - (ProvBasicPersonal + IF(A18>=65, MAX(0, ProvAgeAmount - MAX(0, AE18-ProvAgeThreshold)*ProvAgeClawRate), 0) + IF(OR(H18>0, I18>0), ProvPensionCredit, 0)) * ProvCreditRate)-SurtaxThreshold1)*SurtaxRate1) + MAX(0, (MAX(0, SUMPRODUCT(MAX(MIN(AE18,ProvBracketMax)-ProvBracketMin,0)*ProvBracketRate) - (ProvBasicPersonal + IF(A18>=65, MAX(0, ProvAgeAmount - MAX(0, AE18-ProvAgeThreshold)*ProvAgeClawRate), 0) + IF(OR(H18>0, I18>0), ProvPensionCredit, 0)) * ProvCreditRate)-SurtaxThreshold2)*SurtaxRate2) | AH18: =AF18+AG18 | AI18: =E18+F18+AC18+H18+Z18+T18+V18+AA18-AH18 | AJ18: =AI18-M18-N18-O18 | AK18: =IF(AJ18>0, MIN(AJ18, Assumptions_TfsaAnnualLimit), 0) | AL18: =MAX(0,AL17-Z18)*(1+Assumptions_RealReturn) | AM18: =MAX(0,AM17-T18+AK18)*(1+Assumptions_TfsaReturn) | AN18: =MAX(0,AN17-V18+MAX(0,AJ18-AK18))*(1+Assumptions_NonRegReturn) | AO18: =MAX(0,AO17-AA18)*(1+Assumptions_RealReturn) | AP18: =IF(N18>0, MAX(0, AP17*(1+Assumptions_MortgageRate)-N18), 0) | AQ18: =AL18+AM18+AN18+AO18 | AR18: =AQ18+Assumptions_RealEstateValue-AP18 | AS18: =MAX(0,AS17*MAX(0,AN17-V18)/IF(AN17>0,AN17,1))+MAX(0,AJ18-AK18)
... A62: =A61+1 | B62: =2026+(A62-Assumptions_CurrentAge) | C62: =IF(A62>=Assumptions_RetirementAge,1,0) | D62: =(1+Assumptions_Inflation)^(A62-Assumptions_CurrentAge) | E62: =IF(AND(C62=0,Assumptions_StillWorking=1),Assumptions_EmploymentIncome*D62,0) | F62: =IF(A62>=Assumptions_CppStartAge, Assumptions_CppMonthly*12*IF((Assumptions_CppStartAge-65)*12<0, 1+(Assumptions_CppStartAge-65)*12*CppEarlyReduction, 1+(Assumptions_CppStartAge-65)*12*CppLateIncrease)*D62, 0) | G62: =IF(A62>=Assumptions_OasStartAge, Assumptions_OasMonthly*12*(1+MAX(0, MIN(Assumptions_OasStartAge, OasMaxDeferAge)-OasStdStartAge)*12*OasDeferralBonus)*D62, 0) | H62: =IF(AND(Assumptions_PensionType="db",A62>=Assumptions_DbPensionStartAge), IF(Assumptions_DbPensionIndexed=1, Assumptions_DbPensionAnnual*D62, Assumptions_DbPensionAnnual), 0) | I62: =IF(AND(A62>=72,AL61>0), VLOOKUP(MIN(A62,95),RrifRates,2,TRUE)*AL61, 0) | J62: =IF(AND(Assumptions_MeltdownEnabled=1,A62>=Assumptions_MeltdownStartAge,A62<Assumptions_MeltdownTargetAge), MIN(Assumptions_MeltdownAnnual,AL61), 0) | K62: =MIN(MAX(I62,J62),AL61) | L62: =E62+F62+G62+H62+K62 | M62: =IF(C62=1, Assumptions_MonthlyExpenses*12*(1-Assumptions_ExpenseReduction), Assumptions_MonthlyExpenses*12)*D62 | N62: =IF(AND(AP61>0, (A62-Assumptions_CurrentAge)<Assumptions_MortgageYears), IF(Assumptions_MortgageRate=0, AP61/MAX(1,Assumptions_MortgageYears-(A62-Assumptions_CurrentAge)), AP61*Assumptions_MortgageRate*(1+Assumptions_MortgageRate)^MAX(1,Assumptions_MortgageYears-(A62-Assumptions_CurrentAge))/((1+Assumptions_MortgageRate)^MAX(1,Assumptions_MortgageYears-(A62-Assumptions_CurrentAge))-1)), 0) | O62: =IF(AND(Assumptions_ConsumerDebt>0, A62<Assumptions_ConsumerPayoffAge), IF(Assumptions_ConsumerDebtRate=0, Assumptions_ConsumerDebt/MAX(1,Assumptions_ConsumerPayoffAge-Assumptions_CurrentAge-(A62-Assumptions_CurrentAge)), Assumptions_ConsumerDebt*Assumptions_ConsumerDebtRate*(1+Assumptions_ConsumerDebtRate)^MAX(1,Assumptions_ConsumerPayoffAge-Assumptions_CurrentAge-(A62-Assumptions_CurrentAge))/((1+Assumptions_ConsumerDebtRate)^MAX(1,Assumptions_ConsumerPayoffAge-Assumptions_CurrentAge-(A62-Assumptions_CurrentAge))-1)), 0)+IF(AND(Assumptions_OtherDebt>0, A62<Assumptions_OtherPayoffAge), IF(Assumptions_OtherDebtRate=0, Assumptions_OtherDebt/MAX(1,Assumptions_OtherPayoffAge-Assumptions_CurrentAge-(A62-Assumptions_CurrentAge)), Assumptions_OtherDebt*Assumptions_OtherDebtRate*(1+Assumptions_OtherDebtRate)^MAX(1,Assumptions_OtherPayoffAge-Assumptions_CurrentAge-(A62-Assumptions_CurrentAge))/((1+Assumptions_OtherDebtRate)^MAX(1,Assumptions_OtherPayoffAge-Assumptions_CurrentAge-(A62-Assumptions_CurrentAge))-1)), 0) | P62: =M62+N62+O62 | Q62: =IF(L62<=0, 0, MAX(0, SUMPRODUCT(MAX(MIN(L62,FedBracketMax)-FedBracketMin,0)*FedBracketRate) - (FedBasicPersonal + IF(A62>=65, MAX(0, FedAgeAmount - MAX(0, L62-FedAgeThreshold)*FedAgeClawRate), 0) + IF(OR(H62>0, I62>0), FedPensionCredit, 0)) * FedCreditRate)) | R62: =L62-Q62 | S62: =MAX(0,P62-R62) | T62: =MIN(S62,AM61) | U62: =MAX(0,S62-T62) | V62: =MIN(U62,AN61) | W62: =MAX(0,U62-V62) | X62: =INDEX(FedBracketRate,MATCH(L62,FedBracketMin,1))+INDEX(ProvBracketRate,MATCH(L62,ProvBracketMin,1)) | Y62: =IF(W62>0, MIN(IF(X62>=1, W62, W62/(1-X62)), MAX(0,AL61-K62)), 0) | Z62: =K62+Y62 | AA62: =IF(W62>Y62*(1-X62), MIN(MAX(0,W62-Y62*(1-X62)),AO61), 0) | AB62: =MIN(Assumptions_OasMaxAnnual, MAX(0,(E62+F62+G62+H62+Z62-Assumptions_OasClawbackThresh)*Assumptions_OasClawbackRate)) | AC62: =MAX(0,G62-AB62) | AD62: =V62*IF(AN61>0, MAX(0,1-AS61/AN61), 0)*Assumptions_CapGainsRate | AE62: =E62+F62+AC62+H62+Z62+AD62 | AF62: =MAX(0, SUMPRODUCT(MAX(MIN(AE62,FedBracketMax)-FedBracketMin,0)*FedBracketRate) - (FedBasicPersonal + IF(A62>=65, MAX(0, FedAgeAmount - MAX(0, AE62-FedAgeThreshold)*FedAgeClawRate), 0) + IF(OR(H62>0, I62>0), FedPensionCredit, 0)) * FedCreditRate) | AG62: =MAX(0, SUMPRODUCT(MAX(MIN(AE62,ProvBracketMax)-ProvBracketMin,0)*ProvBracketRate) - (ProvBasicPersonal + IF(A62>=65, MAX(0, ProvAgeAmount - MAX(0, AE62-ProvAgeThreshold)*ProvAgeClawRate), 0) + IF(OR(H62>0, I62>0), ProvPensionCredit, 0)) * ProvCreditRate) + MAX(0, (MAX(0, SUMPRODUCT(MAX(MIN(AE62,ProvBracketMax)-ProvBracketMin,0)*ProvBracketRate) - (ProvBasicPersonal + IF(A62>=65, MAX(0, ProvAgeAmount - MAX(0, AE62-ProvAgeThreshold)*ProvAgeClawRate), 0) + IF(OR(H62>0, I62>0), ProvPensionCredit, 0)) * ProvCreditRate)-SurtaxThreshold1)*SurtaxRate1) + MAX(0, (MAX(0, SUMPRODUCT(MAX(MIN(AE62,ProvBracketMax)-ProvBracketMin,0)*ProvBracketRate) - (ProvBasicPersonal + IF(A62>=65, MAX(0, ProvAgeAmount - MAX(0, AE62-ProvAgeThreshold)*ProvAgeClawRate), 0) + IF(OR(H62>0, I62>0), ProvPensionCredit, 0)) * ProvCreditRate)-SurtaxThreshold2)*SurtaxRate2) | AH62: =AF62+AG62 | AI62: =E62+F62+AC62+H62+Z62+T62+V62+AA62-AH62 | AJ62: =AI62-M62-N62-O62 | AK62: =IF(AJ62>0, MIN(AJ62, Assumptions_TfsaAnnualLimit), 0) | AL62: =MAX(0,AL61-Z62)*(1+Assumptions_RealReturn) | AM62: =MAX(0,AM61-T62+AK62)*(1+Assumptions_TfsaReturn) | AN62: =MAX(0,AN61-V62+MAX(0,AJ62-AK62))*(1+Assumptions_NonRegReturn) | AO62: =MAX(0,AO61-AA62)*(1+Assumptions_RealReturn) | AP62: =IF(N62>0, MAX(0, AP61*(1+Assumptions_MortgageRate)-N62), 0) | AQ62: =AL62+AM62+AN62+AO62 | AR62: =AQ62+Assumptions_RealEstateValue-AP62 | AS62: =MAX(0,AS61*MAX(0,AN61-V62)/IF(AN61>0,AN61,1))+MAX(0,AJ62-AK62)
A64: COLUMN DICTIONARY
A65: Age | B65: Your age in this projection year
A66: Year | B66: Calendar year
A67: Retired? | B67: 1 = retired (no employment income), 0 = still working
A68: Inflation Factor | B68: Cumulative inflation multiplier since today (compounds annually)
A69: Employment | B69: Gross salary, inflation-adjusted. Drops to $0 at retirement age
A70: CPP | B70: Canada Pension Plan income, adjusted for early/late start age
A71: OAS Gross | B71: Old Age Security before clawback, adjusted for deferral bonus
A72: Pension | B72: Defined-benefit pension income (if applicable)
A73: RRIF Min | B73: Mandatory minimum RRSP/RRIF withdrawal after age 71 (CRA rates)
A74: Meltdown | B74: Voluntary RRSP drawdown to reduce future forced RRIF withdrawals
A75: Base RRSP Wd | B75: Greater of RRIF minimum or meltdown amount, capped at RRSP balance
A76: Taxable Before Grossup | B76: Sum of all taxable income sources before extra RRSP withdrawals
... A109: NonReg Cost Basis | B109: Tracks what you originally paid into non-reg accounts, adjusted for withdrawals/deposits. Used to calculate capital gains tax.

Sheet RRIF Rates
A1: After age 71, the government forces you to convert your RRSP to a RRIF and withdraw a minimum percentage every year. These are the CRA-prescribed rates. The percentage increases with age — by 95, you must withdraw 20% per year.
A4: Age | B4: Min Rate | C4: On $100K | D4: On $200K
A5: 55 | B5: 0.028571429 | C5: 2857 | D5: 5714
A6: 56 | B6: 0.029411765 | C6: 2941 | D6: 5882
A7: 57 | B7: 0.03030303 | C7: 3030 | D7: 6061
A8: 58 | B8: 0.03125 | C8: 3125 | D8: 6250
A9: 59 | B9: 0.032258065 | C9: 3226 | D9: 6452
A10: 60 | B10: 0.033333333 | C10: 3333 | D10: 6667
A11: 61 | B11: 0.034482759 | C11: 3448 | D11: 6897
A12: 62 | B12: 0.035714286 | C12: 3571 | D12: 7143
A13: 63 | B13: 0.037037037 | C13: 3704 | D13: 7407
A14: 64 | B14: 0.038461538 | C14: 3846 | D14: 7692
A15: 65 | B15: 0.04 | C15: 4000 | D15: 8000
A16: 66 | B16: 0.041666667 | C16: 4167 | D16: 8333
... A45: 95 | B45: 0.2 | C45: 20000 | D45: 40000
A47: COLUMN DICTIONARY
A48: Age | B48: Your age in this row
A49: Min Rate | B49: CRA-prescribed minimum percentage you must withdraw from your RRIF each year
A50: On $100K | B50: Example: how much you'd have to withdraw if your RRIF balance were $100,000
A51: On $200K | B51: Example: how much you'd have to withdraw if your RRIF balance were $200,000

Sheet Estate
A1: What happens to your money when you die. This shows how much your heirs actually receive after the government takes its share in taxes and probate fees.
A4: ESTATE ANALYSIS AT DEATH
A6: Final Portfolio Balances
A7: RRSP/RRIF Balance | B7: ='Projection'!AL62
A8: TFSA Balance | B8: ='Projection'!AM62
A9: Non-Reg Balance | B9: ='Projection'!AN62
A10: Other Assets | B10: ='Projection'!AO62
A11: Total Portfolio | B11: ='Projection'!AQ62
A12: Real Estate Value | B12: =Assumptions_RealEstateValue
A13: Mortgage Balance | B13: ='Projection'!AP62
A15: Deemed Disposition at Death
A16: RRSP Deemed Income | B16: =B7
A17: Non-Reg Capital Gain | B17: =MAX(0,B9-Assumptions_NonRegCostBasis)*Assumptions_CapGainsRate
A18: Real Estate Cap Gain | B18: =IF(Assumptions_IsPrimaryRes=1, 0, MAX(0,B12-Assumptions_RealEstateCost)*Assumptions_CapGainsRate)
A19: Total Deemed Income | B19: =B16+B17+B18
A21: Tax on Deemed Income
A22: Federal Tax | B22: =MAX(0, SUMPRODUCT(MAX(MIN(B19,FedBracketMax)-FedBracketMin,0)*FedBracketRate) - FedBasicPersonal*FedCreditRate)
A23: Provincial Tax | B23: =MAX(0, SUMPRODUCT(MAX(MIN(B19,ProvBracketMax)-ProvBracketMin,0)*ProvBracketRate) - ProvBasicPersonal*ProvCreditRate) + MAX(0,(MAX(0, SUMPRODUCT(MAX(MIN(B19,ProvBracketMax)-ProvBracketMin,0)*ProvBracketRate) - ProvBasicPersonal*ProvCreditRate)-SurtaxThreshold1)*SurtaxRate1) + MAX(0,(MAX(0, SUMPRODUCT(MAX(MIN(B19,ProvBracketMax)-ProvBracketMin,0)*ProvBracketRate) - ProvBasicPersonal*ProvCreditRate)-SurtaxThreshold2)*SurtaxRate2)
A24: Total Estate Tax | B24: =B22+B23
A26: Probate Fees
A27: Probate Estate | B27: =MAX(0, B11+B12-B8-B13)
A28: Probate Fee | B28: =MIN(B27,50000)*0.005+MAX(0,B27-50000)*0.015
A30: Net Estate Summary
A31: Gross Estate | B31: =B11+B12
A32: Less: Mortgage | B32: =B13
A33: Less: Estate Tax | B33: =B24
A34: Less: Probate Fee | B34: =B28
A35: NET ESTATE | B35: =B11+B12-B13-B24-B28
A37: COLUMN DICTIONARY
A38: RRSP/RRIF at Death | B38: Full balance is treated as income in your final tax return
A39: Deemed Income Tax | B39: Tax owed on RRSP + capital gains as if you sold everything at death
A40: Capital Gains | B40: Taxable gain on non-reg investments and investment real estate (50% inclusion)
A41: Probate Estate | B41: Assets that go through probate (portfolio + real estate - TFSA - mortgage)
A42: Probate Fees | B42: Provincial fee for validating your will (varies by province)
A43: Net to Heirs | B43: What your beneficiaries actually receive after all deductions

Sheet Optimizer
A1: Side-by-side comparison of your current plan vs what the optimizer recommends. Each row shows a different strategy dimension — CPP timing, OAS timing, withdrawal order, or meltdown approach.
A4: OPTIMIZER RESULTS
A6: Optimizer not yet run — navigate to the Optimize tab first.
